{"timestamp": 1682754145283.948, "profitability": [{"name": "CS:GO Weapon Case", "cost": 92.8, "predict_cost": 97.75232040590228, "difference": 5.336552161532635, "total_return": 40.793042607341704, "profitability_ratio": 42.809363634527976, "roi": -57.190636365472024, "average_prices": {"MP7 | Skulls": 16.305925000000002, "AUG | Wings": 17.51141, "SG 553 | Ultraviolet": 18.049400000000002, "Glock-18 | Dragon Tattoo": 108.60871, "USP-S | Dark Water": 84.03208000000001, "M4A1-S | Dark Water": 77.63673000000001, "AK-47 | Case Hardened": 276.98885, "Desert Eagle | Hypnotic": 150.043565, "AWP | Lightning Strike": 714.5469750000001, "Bayonet | Fade": 940.775245, "Bayonet | Slaughter": 762.1189833333333, "Bayonet | Case Hardened": 579.0264300000001, "Bayonet | Urban Masked": 343.15517000000006, "Bayonet | Crimson Web": 495.44675000000007, "Bayonet | Blue Steel": 498.7956, "Bayonet | Stained": 406.29424000000006, "Bayonet | Night": 386.86725, "Bayonet | Safari Mesh": 327.78502000000003, "Bayonet | Forest DDPAT": 300.09444, "Bayonet | Boreal Forest": 327.84270000000004, "Bayonet | Scorched": 325.42941, "Flip Knife | Fade": 1045.9882, "Flip Knife | Slaughter": 556.7705, "Flip Knife | Crimson Web": 295.63783, "Flip Knife | Safari Mesh": 211.25877, "Flip Knife | Case Hardened": 350.51495000000006, "Flip Knife | Night": 279.13901999999996, "Flip Knife | Stained": 253.81400000000002, "Flip Knife | Blue Steel": 290.21262, "Flip Knife | Boreal Forest": 220.27391000000003, "Flip Knife | Forest DDPAT": 225.43328999999997, "Flip Knife | Scorched": 212.70335000000003, "Flip Knife | Urban Masked": 218.21346000000003, "Gut Knife | Fade": 309.73177000000004, "Gut Knife | Case Hardened": 226.46593000000004, "Gut Knife | Slaughter": 223.82513999999998, "Gut Knife | Night": 132.91708, "Gut Knife | Blue Steel": 155.4466, "Gut Knife | Crimson Web": 181.61738, "Gut Knife | Boreal Forest": 123.87463000000002, "Gut Knife | Forest DDPAT": 124.19846000000001, "Gut Knife | Stained": 141.91458, "Gut Knife | Scorched": 126.73970999999997, "Gut Knife | Urban Masked": 131.83136000000002, "Gut Knife | Safari Mesh": 128.94198, "Karambit | Fade": 1639.2760000000003, "Karambit | Slaughter": 1297.1049666666665, "Karambit | Case Hardened": 1045.51831, "Karambit | Crimson Web": 1155.81128, "Karambit | Night": 547.56663, "Karambit | Blue Steel": 943.27921, "Karambit | Stained": 856.75436, "Karambit | Boreal Forest": 592.95549, "Karambit | Forest DDPAT": 590.7430300000001, "Karambit | Urban Masked": 684.7818800000001}}, {"name": "eSports 2013 Case", "cost": 64.62, "predict_cost": 25.09606393862827, "difference": -61.16362745492376, "total_return": 11.366617657540953, "profitability_ratio": 16.937293484638584, "roi": -83.06270651536141, "average_prices": {"M4A4 | Faded Zebra": 3.2801, "MAG-7 | Memento": 3.403203333333334, "FAMAS | Doomkitty": 3.3274000000000004, "Galil AR | Orange DDPAT": 16.46205, "Sawed-Off | Orange DDPAT": 15.750500000000002, "P250 | Splash": 24.483610000000002, "AK-47 | Red Laminate": 64.24331000000001, "AWP | BOOM": 191.60321, "P90 | Death by Kitty": 64.06798, "Bayonet | Fade": 940.775245, "Bayonet | Slaughter": 762.1189833333333, "Bayonet | Case Hardened": 579.0264300000001, "Bayonet | Urban Masked": 343.15517000000006, "Bayonet | Crimson Web": 495.44675000000007, "Bayonet | Blue Steel": 498.7956, "Bayonet | Stained": 406.29424000000006, "Bayonet | Night": 386.86725, "Bayonet | Safari Mesh": 327.78502000000003, "Bayonet | Forest DDPAT": 300.09444, "Bayonet | Boreal Forest": 327.84270000000004, "Bayonet | Scorched": 325.42941, "Flip Knife | Fade": 1045.9882, "Flip Knife | Slaughter": 556.7705, "Flip Knife | Crimson Web": 295.63783, "Flip Knife | Safari Mesh": 211.25877, "Flip Knife | Case Hardened": 350.51495000000006, "Flip Knife | Night": 279.13901999999996, "Flip Knife | Stained": 253.81400000000002, "Flip Knife | Blue Steel": 290.21262, "Flip Knife | Boreal Forest": 220.27391000000003, "Flip Knife | Forest DDPAT": 225.43328999999997, "Flip Knife | Scorched": 212.70335000000003, "Flip Knife | Urban Masked": 218.21346000000003, "Gut Knife | Fade": 309.73177000000004, "Gut Knife | Case Hardened": 226.46593000000004, "Gut Knife | Slaughter": 223.82513999999998, "Gut Knife | Night": 132.91708, "Gut Knife | Blue Steel": 155.4466, "Gut Knife | Crimson Web": 181.61738, "Gut Knife | Boreal Forest": 123.87463000000002, "Gut Knife | Forest DDPAT": 124.19846000000001, "Gut Knife | Stained": 141.91458, "Gut Knife | Scorched": 126.73970999999997, "Gut Knife | Urban Masked": 131.83136000000002, "Gut Knife | Safari Mesh": 128.94198, "Karambit | Fade": 1639.2760000000003, "Karambit | Slaughter": 1297.1049666666665, "Karambit | Case Hardened": 1045.51831, "Karambit | Crimson Web": 1155.81128, "Karambit | Night": 547.56663, "Karambit | Blue Steel": 943.27921, "Karambit | Stained": 856.75436, "Karambit | Boreal Forest": 592.95549, "Karambit | Forest DDPAT": 590.7430300000001, "Karambit | Urban Masked": 684.7818800000001}}, {"name": "Operation Bravo Case", "cost": 68.01, "predict_cost": 54.81652866348981, "difference": -19.399310890325232, "total_return": 23.403668108843288, "profitability_ratio": 33.1966923529692, "roi": -66.80330764703079, "average_prices": {"SG 553 | Wave Spray": 5.89827, "Dual Berettas | Black Limba": 5.71846, "Nova | Tempest": 7.718196666666667, "Galil AR | Shattered": 5.87693, "UMP-45 | Bone Pile": 7.34816, "G3SG1 | Demeter": 6.03129, "USP-S | Overgrowth": 36.50527, "M4A4 | Zirka": 35.020120000000006, "MAC-10 | Graven": 34.25032, "M4A1-S | Bright Water": 37.05163, "P90 | Emerald Dragon": 150.55867, "P2000 | Ocean Foam": 225.47201, "AWP | Graphite": 314.71550500000006, "AK-47 | Fire Serpent": 1140.2605600000002, "Desert Eagle | Golden Koi": 115.65238, "Bayonet | Fade": 940.775245, "Bayonet | Slaughter": 762.1189833333333, "Bayonet | Case Hardened": 579.0264300000001, "Bayonet | Urban Masked": 343.15517000000006, "Bayonet | Crimson Web": 495.44675000000007, "Bayonet | Blue Steel": 498.7956, "Bayonet | Stained": 406.29424000000006, "Bayonet | Night": 386.86725, "Bayonet | Safari Mesh": 327.78502000000003, "Bayonet | Forest DDPAT": 300.09444, "Bayonet | Boreal Forest": 327.84270000000004, "Bayonet | Scorched": 325.42941, "Flip Knife | Fade": 1045.9882, "Flip Knife | Slaughter": 556.7705, "Flip Knife | Crimson Web": 295.63783, "Flip Knife | Safari Mesh": 211.25877, "Flip Knife | Case Hardened": 350.51495000000006, "Flip Knife | Night": 279.13901999999996, "Flip Knife | Stained": 253.81400000000002, "Flip Knife | Blue Steel": 290.21262, "Flip Knife | Boreal Forest": 220.27391000000003, "Flip Knife | Forest DDPAT": 225.43328999999997, "Flip Knife | Scorched": 212.70335000000003, "Flip Knife | Urban Masked": 218.21346000000003, "Gut Knife | Fade": 309.73177000000004, "Gut Knife | Case Hardened": 226.46593000000004, "Gut Knife | Slaughter": 223.82513999999998, "Gut Knife | Night": 132.91708, "Gut Knife | Blue Steel": 155.4466, "Gut Knife | Crimson Web": 181.61738, "Gut Knife | Boreal Forest": 123.87463000000002, "Gut Knife | Forest DDPAT": 124.19846000000001, "Gut Knife | Stained": 141.91458, "Gut Knife | Scorched": 126.73970999999997, "Gut Knife | Urban Masked": 131.83136000000002, "Gut Knife | Safari Mesh": 128.94198, "Karambit | Fade": 1639.2760000000003, "Karambit | Slaughter": 1297.1049666666665, "Karambit | Case Hardened": 1045.51831, "Karambit | Crimson Web": 1155.81128, "Karambit | Night": 547.56663, "Karambit | Blue Steel": 943.27921, "Karambit | Stained": 856.75436, "Karambit | Boreal Forest": 592.95549, "Karambit | Forest DDPAT": 590.7430300000001, "Karambit | Urban Masked": 684.7818800000001}}, {"name": "CS:GO Weapon Case 2", "cost": 9.89, "predict_cost": 18.146831904074116, "difference": 83.48667243755425, "total_return": 8.552117367181701, "profitability_ratio": 69.08010797400405, "roi": -30.91989202599596, "average_prices": {"Tec-9 | Blue Titanium": 4.921, "M4A1-S | Blood Tiger": 4.599193333333333, "FAMAS | Hexane": 3.20952, "P250 | Hive": 3.4462433333333333, "SCAR-20 | Crimson Web": 3.4741599999999995, "Five-SeveN | Case Hardened": 13.045509999999997, "MP9 | Hypnotic": 15.683945000000001, "Nova | Graphite": 11.468235, "Dual Berettas | Hemoglobin": 10.962179999999998, "P90 | Cold Blooded": 64.52413, "USP-S | Serum": 43.665276666666664, "SSG 08 | Blood in the Water": 71.60125666666666, "Bayonet | Fade": 940.775245, "Bayonet | Slaughter": 762.1189833333333, "Bayonet | Case Hardened": 579.0264300000001, "Bayonet | Urban Masked": 343.15517000000006, "Bayonet | Crimson Web": 495.44675000000007, "Bayonet | Blue Steel": 498.7956, "Bayonet | Stained": 406.29424000000006, "Bayonet | Night": 386.86725, "Bayonet | Safari Mesh": 327.78502000000003, "Bayonet | Forest DDPAT": 300.09444, "Bayonet | Boreal Forest": 327.84270000000004, "Bayonet | Scorched": 325.42941, "Flip Knife | Fade": 1045.9882, "Flip Knife | Slaughter": 556.7705, "Flip Knife | Crimson Web": 295.63783, "Flip Knife | Safari Mesh": 211.25877, "Flip Knife | Case Hardened": 350.51495000000006, "Flip Knife | Night": 279.13901999999996, "Flip Knife | Stained": 253.81400000000002, "Flip Knife | Blue Steel": 290.21262, "Flip Knife | Boreal Forest": 220.27391000000003, "Flip Knife | Forest DDPAT": 225.43328999999997, "Flip Knife | Scorched": 212.70335000000003, "Flip Knife | Urban Masked": 218.21346000000003, "Gut Knife | Fade": 309.73177000000004, "Gut Knife | Case Hardened": 226.46593000000004, "Gut Knife | Slaughter": 223.82513999999998, "Gut Knife | Night": 132.91708, "Gut Knife | Blue Steel": 155.4466, "Gut Knife | Crimson Web": 181.61738, "Gut Knife | Boreal Forest": 123.87463000000002, "Gut Knife | Forest DDPAT": 124.19846000000001, "Gut Knife | Stained": 141.91458, "Gut Knife | Scorched": 126.73970999999997, "Gut Knife | Urban Masked": 131.83136000000002, "Gut Knife | Safari Mesh": 128.94198, "Karambit | Fade": 1639.2760000000003, "Karambit | Slaughter": 1297.1049666666665, "Karambit | Case Hardened": 1045.51831, "Karambit | Crimson Web": 1155.81128, "Karambit | Night": 547.56663, "Karambit | Blue Steel": 943.27921, "Karambit | Stained": 856.75436, "Karambit | Boreal Forest": 592.95549, "Karambit | Forest DDPAT": 590.7430300000001, "Karambit | Urban Masked": 684.7818800000001}}, {"name": "eSports 2013 Winter Case", "cost": 8.66, "predict_cost": 13.15740912686175, "difference": 51.933130795170335, "total_return": 6.531357118370954, "profitability_ratio": 58.57719388673501, "roi": -41.42280611326499, "average_prices": {"Galil AR | Blue Titanium": 2.6360000000000006, "Five-SeveN | Nightshade": 1.5191500000000004, "PP-Bizon | Water Sigil": 1.40244, "Nova | Ghost Camo": 1.5527999999999997, "G3SG1 | Azure Zebra": 1.60839, "P250 | Steel Disruption": 1.8973033333333333, "AK-47 | Blue Laminate": 13.918149999999999, "P90 | Blind Spot": 9.3111, "FAMAS | Afterimage": 40.72907, "AWP | Electric Hive": 56.10527999999999, "Desert Eagle | Cobalt Disruption": 85.7925, "M4A4 | X-Ray": 21.118153333333332, "Bayonet | Fade": 940.775245, "Bayonet | Slaughter": 762.1189833333333, "Bayonet | Case Hardened": 579.0264300000001, "Bayonet | Urban Masked": 343.15517000000006, "Bayonet | Crimson Web": 495.44675000000007, "Bayonet | Blue Steel": 498.7956, "Bayonet | Stained": 406.29424000000006, "Bayonet | Night": 386.86725, "Bayonet | Safari Mesh": 327.78502000000003, "Bayonet | Forest DDPAT": 300.09444, "Bayonet | Boreal Forest": 327.84270000000004, "Bayonet | Scorched": 325.42941, "Flip Knife | Fade": 1045.9882, "Flip Knife | Slaughter": 556.7705, "Flip Knife | Crimson Web": 295.63783, "Flip Knife | Safari Mesh": 211.25877, "Flip Knife | Case Hardened": 350.51495000000006, "Flip Knife | Night": 279.13901999999996, "Flip Knife | Stained": 253.81400000000002, "Flip Knife | Blue Steel": 290.21262, "Flip Knife | Boreal Forest": 220.27391000000003, "Flip Knife | Forest DDPAT": 225.43328999999997, "Flip Knife | Scorched": 212.70335000000003, "Flip Knife | Urban Masked": 218.21346000000003, "Gut Knife | Fade": 309.73177000000004, "Gut Knife | Case Hardened": 226.46593000000004, "Gut Knife | Slaughter": 223.82513999999998, "Gut Knife | Night": 132.91708, "Gut Knife | Blue Steel": 155.4466, "Gut Knife | Crimson Web": 181.61738, "Gut Knife | Boreal Forest": 123.87463000000002, "Gut Knife | Forest DDPAT": 124.19846000000001, "Gut Knife | Stained": 141.91458, "Gut Knife | Scorched": 126.73970999999997, "Gut Knife | Urban Masked": 131.83136000000002, "Gut Knife | Safari Mesh": 128.94198, "Karambit | Fade": 1639.2760000000003, "Karambit | Slaughter": 1297.1049666666665, "Karambit | Case Hardened": 1045.51831, "Karambit | Crimson Web": 1155.81128, "Karambit | Night": 547.56663, "Karambit | Blue Steel": 943.27921, "Karambit | Stained": 856.75436, "Karambit | Boreal Forest": 592.95549, "Karambit | Forest DDPAT": 590.7430300000001, "Karambit | Urban Masked": 684.7818800000001}}, {"name": "Winter Offensive Weapon Case", "cost": 8.09, "predict_cost": 9.354071080694823, "difference": 15.625106065448986, "total_return": 4.990971651020821, "profitability_ratio": 47.17364509471476, "roi": -52.82635490528524, "average_prices": {"Galil AR | Sandstorm": 1.4503875000000004, "Five-SeveN | Kami": 1.3154966666666665, "M249 | Magma": 0.95321, "PP-Bizon | Cobalt Halftone": 0.9580900000000001, "FAMAS | Pulse": 7.176009999999999, "Dual Berettas | Marina": 6.3333, "MP9 | Rose Iron": 7.351663333333334, "Nova | Rising Skull": 5.3915299999999995, "M4A1-S | Guardian": 29.13253, "P250 | Mehndi": 19.62525, "AWP | Redline": 66.84183666666667, "M4A4 | Asiimov": 176.90735000000006, "Sawed-Off | The Kraken": 9.50724, "Bayonet | Fade": 940.775245, "Bayonet | Slaughter": 762.1189833333333, "Bayonet | Case Hardened": 579.0264300000001, "Bayonet | Urban Masked": 343.15517000000006, "Bayonet | Crimson Web": 495.44675000000007, "Bayonet | Blue Steel": 498.7956, "Bayonet | Stained": 406.29424000000006, "Bayonet | Night": 386.86725, "Bayonet | Safari Mesh": 327.78502000000003, "Bayonet | Forest DDPAT": 300.09444, "Bayonet | Boreal Forest": 327.84270000000004, "Bayonet | Scorched": 325.42941, "Flip Knife | Fade": 1045.9882, "Flip Knife | Slaughter": 556.7705, "Flip Knife | Crimson Web": 295.63783, "Flip Knife | Safari Mesh": 211.25877, "Flip Knife | Case Hardened": 350.51495000000006, "Flip Knife | Night": 279.13901999999996, "Flip Knife | Stained": 253.81400000000002, "Flip Knife | Blue Steel": 290.21262, "Flip Knife | Boreal Forest": 220.27391000000003, "Flip Knife | Forest DDPAT": 225.43328999999997, "Flip Knife | Scorched": 212.70335000000003, "Flip Knife | Urban Masked": 218.21346000000003, "Gut Knife | Fade": 309.73177000000004, "Gut Knife | Case Hardened": 226.46593000000004, "Gut Knife | Slaughter": 223.82513999999998, "Gut Knife | Night": 132.91708, "Gut Knife | Blue Steel": 155.4466, "Gut Knife | Crimson Web": 181.61738, "Gut Knife | Boreal Forest": 123.87463000000002, "Gut Knife | Forest DDPAT": 124.19846000000001, "Gut Knife | Stained": 141.91458, "Gut Knife | Scorched": 126.73970999999997, "Gut Knife | Urban Masked": 131.83136000000002, "Gut Knife | Safari Mesh": 128.94198, "Karambit | Fade": 1639.2760000000003, "Karambit | Slaughter": 1297.1049666666665, "Karambit | Case Hardened": 1045.51831, "Karambit | Crimson Web": 1155.81128, "Karambit | Night": 547.56663, "Karambit | Blue Steel": 943.27921, "Karambit | Stained": 856.75436, "Karambit | Boreal Forest": 592.95549, "Karambit | Forest DDPAT": 590.7430300000001, "Karambit | Urban Masked": 684.7818800000001}}, {"name": "CS:GO Weapon Case 3", "cost": 7.73, "predict_cost": 13.80602617271942, "difference": 78.60318464061345, "total_return": 6.794052744998637, "profitability_ratio": 66.47801120350915, "roi": -33.52198879649084, "average_prices": {"CZ75-Auto | Crimson Web": 2.5077000000000003, "P2000 | Red FragCam": 1.6409699999999998, "Dual Berettas | Panther": 1.5980300000000003, "USP-S | Stainless": 9.22094, "Glock-18 | Blue Fissure": 2.6517000000000004, "CZ75-Auto | Tread Plate": 8.51845, "Tec-9 | Titanium Bit": 8.53504, "Desert Eagle | Heirloom": 8.005920000000001, "Five-SeveN | Copper Galaxy": 12.737446666666665, "CZ75-Auto | The Fuschia Is Now": 33.3978, "P250 | Undertow": 43.38994666666667, "CZ75-Auto | Victoria": 9.43267, "Bayonet | Fade": 940.775245, "Bayonet | Slaughter": 762.1189833333333, "Bayonet | Case Hardened": 579.0264300000001, "Bayonet | Urban Masked": 343.15517000000006, "Bayonet | Crimson Web": 495.44675000000007, "Bayonet | Blue Steel": 498.7956, "Bayonet | Stained": 406.29424000000006, "Bayonet | Night": 386.86725, "Bayonet | Safari Mesh": 327.78502000000003, "Bayonet | Forest DDPAT": 300.09444, "Bayonet | Boreal Forest": 327.84270000000004, "Bayonet | Scorched": 325.42941, "Flip Knife | Fade": 1045.9882, "Flip Knife | Slaughter": 556.7705, "Flip Knife | Crimson Web": 295.63783, "Flip Knife | Safari Mesh": 211.25877, "Flip Knife | Case Hardened": 350.51495000000006, "Flip Knife | Night": 279.13901999999996, "Flip Knife | Stained": 253.81400000000002, "Flip Knife | Blue Steel": 290.21262, "Flip Knife | Boreal Forest": 220.27391000000003, "Flip Knife | Forest DDPAT": 225.43328999999997, "Flip Knife | Scorched": 212.70335000000003, "Flip Knife | Urban Masked": 218.21346000000003, "Gut Knife | Fade": 309.73177000000004, "Gut Knife | Case Hardened": 226.46593000000004, "Gut Knife | Slaughter": 223.82513999999998, "Gut Knife | Night": 132.91708, "Gut Knife | Blue Steel": 155.4466, "Gut Knife | Crimson Web": 181.61738, "Gut Knife | Boreal Forest": 123.87463000000002, "Gut Knife | Forest DDPAT": 124.19846000000001, "Gut Knife | Stained": 141.91458, "Gut Knife | Scorched": 126.73970999999997, "Gut Knife | Urban Masked": 131.83136000000002, "Gut Knife | Safari Mesh": 128.94198, "Karambit | Fade": 1639.2760000000003, "Karambit | Slaughter": 1297.1049666666665, "Karambit | Case Hardened": 1045.51831, "Karambit | Crimson Web": 1155.81128, "Karambit | Night": 547.56663, "Karambit | Blue Steel": 943.27921, "Karambit | Stained": 856.75436, "Karambit | Boreal Forest": 592.95549, "Karambit | Forest DDPAT": 590.7430300000001, "Karambit | Urban Masked": 684.7818800000001}}, {"name": "Operation Phoenix Weapon Case", "cost": 3.13, "predict_cost": 5.1492587918683626, "difference": 64.51306044307869, "total_return": 3.287985572996231, "profitability_ratio": 58.50508137003969, "roi": -41.49491862996031, "average_prices": {"UMP-45 | Corporal": 0.34048999999999996, "Negev | Terrain": 0.34941999999999995, "Tec-9 | Sandstorm": 0.5985474999999999, "MAG-7 | Heaven Guard": 0.35312, "MAC-10 | Heat": 2.676, "SG 553 | Pulse": 2.7826750000000002, "FAMAS | Sergeant": 2.7392025, "USP-S | Guardian": 3.9396266666666664, "AK-47 | Redline": 47.2996125, "P90 | Trigon": 12.3060875, "Nova | Antique": 12.654413333333332, "AWP | Asiimov": 158.92995, "AUG | Chameleon": 5.418540000000001, "Bayonet | Fade": 940.775245, "Bayonet | Slaughter": 762.1189833333333, "Bayonet | Case Hardened": 579.0264300000001, "Bayonet | Urban Masked": 343.15517000000006, "Bayonet | Crimson Web": 495.44675000000007, "Bayonet | Blue Steel": 498.7956, "Bayonet | Stained": 406.29424000000006, "Bayonet | Night": 386.86725, "Bayonet | Safari Mesh": 327.78502000000003, "Bayonet | Forest DDPAT": 300.09444, "Bayonet | Boreal Forest": 327.84270000000004, "Bayonet | Scorched": 325.42941, "Flip Knife | Fade": 1045.9882, "Flip Knife | Slaughter": 556.7705, "Flip Knife | Crimson Web": 295.63783, "Flip Knife | Safari Mesh": 211.25877, "Flip Knife | Case Hardened": 350.51495000000006, "Flip Knife | Night": 279.13901999999996, "Flip Knife | Stained": 253.81400000000002, "Flip Knife | Blue Steel": 290.21262, "Flip Knife | Boreal Forest": 220.27391000000003, "Flip Knife | Forest DDPAT": 225.43328999999997, "Flip Knife | Scorched": 212.70335000000003, "Flip Knife | Urban Masked": 218.21346000000003, "Gut Knife | Fade": 309.73177000000004, "Gut Knife | Case Hardened": 226.46593000000004, "Gut Knife | Slaughter": 223.82513999999998, "Gut Knife | Night": 132.91708, "Gut Knife | Blue Steel": 155.4466, "Gut Knife | Crimson Web": 181.61738, "Gut Knife | Boreal Forest": 123.87463000000002, "Gut Knife | Forest DDPAT": 124.19846000000001, "Gut Knife | Stained": 141.91458, "Gut Knife | Scorched": 126.73970999999997, "Gut Knife | Urban Masked": 131.83136000000002, "Gut Knife | Safari Mesh": 128.94198, "Karambit | Fade": 1639.2760000000003, "Karambit | Slaughter": 1297.1049666666665, "Karambit | Case Hardened": 1045.51831, "Karambit | Crimson Web": 1155.81128, "Karambit | Night": 547.56663, "Karambit | Blue Steel": 943.27921, "Karambit | Stained": 856.75436, "Karambit | Boreal Forest": 592.95549, "Karambit | Forest DDPAT": 590.7430300000001, "Karambit | Urban Masked": 684.7818800000001}}, {"name": "Huntsman Weapon Case", "cost": 10.45, "predict_cost": 11.33983378993578, "difference": 8.515155884552922, "total_return": 5.795223069588085, "profitability_ratio": 44.7853405686869, "roi": -55.214659431313095, "average_prices": {"Tec-9 | Isaac": 2.0750800000000003, "SSG 08 | Slashed": 0.9786175, "Galil AR | Kami": 1.39666, "CZ75-Auto | Twist": 1.32609, "P90 | Module": 1.5977933333333332, "P2000 | Pulse": 1.3917800000000002, "AUG | Torque": 7.87449, "PP-Bizon | Antique": 8.42348, "XM1014 | Heaven Guard": 7.953440000000001, "MAC-10 | Tatter": 7.733200000000001, "M4A1-S | Atomic Alloy": 43.242940000000004, "SCAR-20 | Cyrex": 43.76663, "USP-S | Caiman": 48.342600000000004, "AK-47 | Vulcan": 373.86732000000006, "M4A4 | Desert-Strike": 6.901750000000001, "Huntsman Knife | Slaughter": 435.80510333333336, "Huntsman Knife | Fade": 658.027685, "Huntsman Knife | Case Hardened": 316.04437999999993, "Huntsman Knife | Crimson Web": 365.42247, "Huntsman Knife | Blue Steel": 249.64794, "Huntsman Knife | Night": 209.78706999999997, "Huntsman Knife | Stained": 181.93472000000003, "Huntsman Knife | Boreal Forest": 156.98817, "Huntsman Knife | Safari Mesh": 161.95451, "Huntsman Knife | Forest DDPAT": 159.26363000000003, "Huntsman Knife | Scorched": 159.66655, "Huntsman Knife | Urban Masked": 181.64909000000003}}, {"name": "Operation Breakout Weapon Case", "cost": 6.91, "predict_cost": 5.624311232082977, "difference": -18.606205034978622, "total_return": 3.4803860028957754, "profitability_ratio": 37.02538300952952, "roi": -62.97461699047048, "average_prices": {"MP7 | Urban Hazard": 0.17506000000000002, "Negev | Desert-Strike": 0.16723, "P2000 | Ivory": 0.17099000000000003, "SSG 08 | Abyss": 0.68107, "UMP-45 | Labyrinth": 0.21491000000000002, "PP-Bizon | Osiris": 0.8976700000000001, "CZ75-Auto | Tigris": 0.9034200000000001, "Nova | Koi": 1.2833700000000001, "P250 | Supernova": 1.16009, "Desert Eagle | Conspiracy": 8.539079999999998, "Five-SeveN | Fowl Play": 3.4692799999999995, "Glock-18 | Water Elemental": 9.396840000000001, "P90 | Asiimov": 15.806700000000001, "M4A1-S | Cyrex": 25.695130000000002, "Butterfly Knife | Fade": 1572.430365, "Butterfly Knife | Slaughter": 1855.4264766666665, "Butterfly Knife | Crimson Web": 1290.4666100000002, "Butterfly Knife | Case Hardened": 1199.80331, "Butterfly Knife | Blue Steel": 1212.17775, "Butterfly Knife | Night": 946.94185, "Butterfly Knife | Stained": 981.08955, "Butterfly Knife | Boreal Forest": 709.1499600000001, "Butterfly Knife | Urban Masked": 865.5201800000001, "Butterfly Knife | Scorched": 623.04202, "Butterfly Knife | Forest DDPAT": 809.0053300000001, "Butterfly Knife | Safari Mesh": 719.5527699999999}}, {"name": "eSports 2014 Summer Case", "cost": 6.95, "predict_cost": 8.284323671657742, "difference": 19.198901750471098, "total_return": 4.55771451147287, "profitability_ratio": 48.280874062212604, "roi": -51.7191259377874, "average_prices": {"SSG 08 | Dark Water": 1.6340000000000001, "MAC-10 | Ultraviolet": 2.62359, "USP-S | Blood Tiger": 2.539026666666667, "CZ75-Auto | Hexane": 1.7915700000000003, "Negev | Bratatat": 1.5563600000000002, "XM1014 | Red Python": 1.255035, "PP-Bizon | Blue Streak": 2.3935299999999997, "P90 | Virus": 1.96506, "MP7 | Ocean Foam": 4.5287749999999996, "Glock-18 | Steel Disruption": 4.478386666666666, "Desert Eagle | Crimson Web": 22.505390000000002, "AUG | Bengal Tiger": 8.420169999999999, "Nova | Bloomstick": 11.602240000000002, "AWP | Corticera": 27.471339999999998, "P2000 | Corticera": 9.18727, "M4A4 | Bullet Rain": 22.90683, "AK-47 | Jaguar": 58.401320000000005, "Bayonet | Fade": 940.775245, "Bayonet | Slaughter": 762.1189833333333, "Bayonet | Case Hardened": 579.0264300000001, "Bayonet | Urban Masked": 343.15517000000006, "Bayonet | Crimson Web": 495.44675000000007, "Bayonet | Blue Steel": 498.7956, "Bayonet | Stained": 406.29424000000006, "Bayonet | Night": 386.86725, "Bayonet | Safari Mesh": 327.78502000000003, "Bayonet | Forest DDPAT": 300.09444, "Bayonet | Boreal Forest": 327.84270000000004, "Bayonet | Scorched": 325.42941, "Flip Knife | Fade": 1045.9882, "Flip Knife | Slaughter": 556.7705, "Flip Knife | Crimson Web": 295.63783, "Flip Knife | Safari Mesh": 211.25877, "Flip Knife | Case Hardened": 350.51495000000006, "Flip Knife | Night": 279.13901999999996, "Flip Knife | Stained": 253.81400000000002, "Flip Knife | Blue Steel": 290.21262, "Flip Knife | Boreal Forest": 220.27391000000003, "Flip Knife | Forest DDPAT": 225.43328999999997, "Flip Knife | Scorched": 212.70335000000003, "Flip Knife | Urban Masked": 218.21346000000003, "Gut Knife | Fade": 309.73177000000004, "Gut Knife | Case Hardened": 226.46593000000004, "Gut Knife | Slaughter": 223.82513999999998, "Gut Knife | Night": 132.91708, "Gut Knife | Blue Steel": 155.4466, "Gut Knife | Crimson Web": 181.61738, "Gut Knife | Boreal Forest": 123.87463000000002, "Gut Knife | Forest DDPAT": 124.19846000000001, "Gut Knife | Stained": 141.91458, "Gut Knife | Scorched": 126.73970999999997, "Gut Knife | Urban Masked": 131.83136000000002, "Gut Knife | Safari Mesh": 128.94198, "Karambit | Fade": 1639.2760000000003, "Karambit | Slaughter": 1297.1049666666665, "Karambit | Case Hardened": 1045.51831, "Karambit | Crimson Web": 1155.81128, "Karambit | Night": 547.56663, "Karambit | Blue Steel": 943.27921, "Karambit | Stained": 856.75436, "Karambit | Boreal Forest": 592.95549, "Karambit | Forest DDPAT": 590.7430300000001, "Karambit | Urban Masked": 684.7818800000001}}, {"name": "Operation Vanguard Weapon Case", "cost": 2.48, "predict_cost": 4.175137000164175, "difference": 68.35229839371672, "total_return": 2.8934576522182036, "profitability_ratio": 58.21846382732804, "roi": -41.78153617267197, "average_prices": {"G3SG1 | Murky": 0.65035, "MAG-7 | Firestarter": 0.8122299999999999, "MP9 | Dart": 0.6791600000000001, "Five-SeveN | Urban Hazard": 1.1515866666666668, "UMP-45 | Delusion": 0.85919, "Glock-18 | Grinder": 2.7213366666666667, "M4A1-S | Basilisk": 7.213580000000001, "M4A4 | Griffin": 3.78456, "Sawed-Off | Highwayman": 1.0940599999999998, "P250 | Cartel": 7.977410000000001, "SCAR-20 | Cardiac": 5.75953, "XM1014 | Tranquility": 6.707160000000001, "AK-47 | Wasteland Rebel": 59.328920000000004, "P2000 | Fire Elemental": 15.85413, "Bayonet | Fade": 940.775245, "Bayonet | Slaughter": 762.1189833333333, "Bayonet | Case Hardened": 579.0264300000001, "Bayonet | Urban Masked": 343.15517000000006, "Bayonet | Crimson Web": 495.44675000000007, "Bayonet | Blue Steel": 498.7956, "Bayonet | Stained": 406.29424000000006, "Bayonet | Night": 386.86725, "Bayonet | Safari Mesh": 327.78502000000003, "Bayonet | Scorched": 325.42941, "Bayonet | Forest DDPAT": 300.09444, "Bayonet | Boreal Forest": 327.84270000000004, "Flip Knife | Fade": 1045.9882, "Flip Knife | Slaughter": 556.7705, "Flip Knife | Crimson Web": 295.63783, "Flip Knife | Safari Mesh": 211.25877, "Flip Knife | Case Hardened": 350.51495000000006, "Flip Knife | Night": 279.13901999999996, "Flip Knife | Stained": 253.81400000000002, "Flip Knife | Blue Steel": 290.21262, "Flip Knife | Boreal Forest": 220.27391000000003, "Flip Knife | Forest DDPAT": 225.43328999999997, "Flip Knife | Scorched": 212.70335000000003, "Flip Knife | Urban Masked": 218.21346000000003, "Gut Knife | Fade": 309.73177000000004, "Gut Knife | Case Hardened": 226.46593000000004, "Gut Knife | Slaughter": 223.82513999999998, "Gut Knife | Night": 132.91708, "Gut Knife | Blue Steel": 155.4466, "Gut Knife | Crimson Web": 181.61738, "Gut Knife | Boreal Forest": 123.87463000000002, "Gut Knife | Forest DDPAT": 124.19846000000001, "Gut Knife | Stained": 141.91458, "Gut Knife | Scorched": 126.73970999999997, "Gut Knife | Urban Masked": 131.83136000000002, "Gut Knife | Safari Mesh": 128.94198, "Karambit | Fade": 1639.2760000000003, "Karambit | Slaughter": 1297.1049666666665, "Karambit | Case Hardened": 1045.51831, "Karambit | Crimson Web": 1155.81128, "Karambit | Night": 547.56663, "Karambit | Blue Steel": 943.27921, "Karambit | Stained": 856.75436, "Karambit | Boreal Forest": 592.95549, "Karambit | Forest DDPAT": 590.7430300000001, "Karambit | Urban Masked": 684.7818800000001}}, {"name": "Chroma Case", "cost": 3.07, "predict_cost": 4.6803801947727335, "difference": 52.45538093722259, "total_return": 3.098085604034617, "profitability_ratio": 55.72096410134203, "roi": -44.27903589865797, "average_prices": {"Glock-18 | Catacombs": 0.6366200000000001, "M249 | System Lock": 0.3202, "MP9 | Deadly Poison": 0.38445, "SCAR-20 | Grotto": 0.34731000000000006, "XM1014 | Quicksilver": 0.32219999999999993, "Dual Berettas | Urban Shock": 1.94997, "Desert Eagle | Naga": 2.48808, "MAC-10 | Malachite": 1.9306400000000004, "Sawed-Off | Serenity": 1.8971500000000001, "AK-47 | Cartel": 15.39292, "M4A4 | \u9f8d\u738b (Dragon King)": 13.87729, "P250 | Muertos": 7.04976, "Galil AR | Chatterbox": 36.82014, "Bayonet | Marble Fade": 1267.5693750000003, "Bayonet | Tiger Tooth": 874.10804, "Bayonet | Doppler": 1046.49116, "Bayonet | Rust Coat": 408.12614, "Bayonet | Damascus Steel": 475.17399, "Bayonet | Ultraviolet": 395.75064000000003, "Flip Knife | Marble Fade": 813.4687700000001, "Flip Knife | Tiger Tooth": 694.683315, "Flip Knife | Doppler": 660.472695, "Flip Knife | Ultraviolet": 312.68095, "Flip Knife | Damascus Steel": 289.62934, "Flip Knife | Rust Coat": 279.49622, "Gut Knife | Doppler": 279.918005, "Gut Knife | Ultraviolet": 142.20686000000003, "Gut Knife | Marble Fade": 238.581835, "Gut Knife | Tiger Tooth": 231.88279, "Gut Knife | Damascus Steel": 163.27633, "Gut Knife | Rust Coat": 133.35420000000002, "Karambit | Marble Fade": 1422.182575, "Karambit | Tiger Tooth": 1550.0703750000002, "Karambit | Doppler": 1396.00261, "Karambit | Damascus Steel": 1001.00277, "Karambit | Ultraviolet": 931.37674, "Karambit | Rust Coat": 677.2980000000001, "M9 Bayonet | Marble Fade": 763.6561450000002, "M9 Bayonet | Doppler": 1271.5573450000002, "M9 Bayonet | Tiger Tooth": 1725.0533099999998, "M9 Bayonet | Damascus Steel": 757.3922600000002, "M9 Bayonet | Ultraviolet": 650.58983, "M9 Bayonet | Rust Coat": 541.52038}}, {"name": "Chroma 2 Case", "cost": 2.27, "predict_cost": 4.269563350097876, "difference": 88.08649119373902, "total_return": 2.9317011571097504, "profitability_ratio": 61.59036044348215, "roi": -38.409639556517845, "average_prices": {"AK-47 | Elite Build": 2.4307999999999996, "MP7 | Armor Core": 0.17910000000000004, "Desert Eagle | Bronze Deco": 0.8058099999999999, "P250 | Valence": 0.28423000000000004, "Negev | Man-o'-war": 0.194745, "Sawed-Off | Origami": 0.18227000000000002, "AWP | Worm God": 2.51572, "MAG-7 | Heat": 0.7184499999999999, "CZ75-Auto | Pole Position": 0.67142, "UMP-45 | Grand Prix": 0.454, "Five-SeveN | Monkey Business": 6.30958, "Galil AR | Eco": 10.748349999999999, "FAMAS | Djinn": 3.7828899999999996, "M4A1-S | Hyper Beast": 42.78147, "MAC-10 | Neon Rider": 9.90502, "Bayonet | Marble Fade": 1267.5693750000003, "Bayonet | Tiger Tooth": 874.10804, "Bayonet | Doppler": 1046.49116, "Bayonet | Rust Coat": 408.12614, "Bayonet | Damascus Steel": 475.17399, "Bayonet | Ultraviolet": 395.75064000000003, "Flip Knife | Marble Fade": 813.4687700000001, "Flip Knife | Tiger Tooth": 694.683315, "Flip Knife | Doppler": 660.472695, "Flip Knife | Ultraviolet": 312.68095, "Flip Knife | Damascus Steel": 289.62934, "Flip Knife | Rust Coat": 279.49622, "Gut Knife | Doppler": 279.918005, "Gut Knife | Ultraviolet": 142.20686000000003, "Gut Knife | Marble Fade": 238.581835, "Gut Knife | Tiger Tooth": 231.88279, "Gut Knife | Damascus Steel": 163.27633, "Gut Knife | Rust Coat": 133.35420000000002, "Karambit | Marble Fade": 1422.182575, "Karambit | Tiger Tooth": 1550.0703750000002, "Karambit | Doppler": 1396.00261, "Karambit | Damascus Steel": 1001.00277, "Karambit | Ultraviolet": 931.37674, "Karambit | Rust Coat": 677.2980000000001, "M9 Bayonet | Marble Fade": 763.6561450000002, "M9 Bayonet | Doppler": 1271.5573450000002, "M9 Bayonet | Tiger Tooth": 1725.0533099999998, "M9 Bayonet | Damascus Steel": 757.3922600000002, "M9 Bayonet | Ultraviolet": 650.58983, "M9 Bayonet | Rust Coat": 541.52038}}, {"name": "Falchion Case", "cost": 1.11, "predict_cost": 2.0758559679442152, "difference": 87.0140511661455, "total_return": 2.0432303112185277, "profitability_ratio": 56.75639753384798, "roi": -43.24360246615201, "average_prices": {"Galil AR | Rocket Pop": 1.2162699999999997, "Glock-18 | Bunsen Burner": 0.8330300000000002, "Nova | Ranger": 0.26881, "P90 | Elite Build": 0.30815, "UMP-45 | Riot": 0.27568000000000004, "USP-S | Torque": 1.5014600000000002, "FAMAS | Neural Net": 1.17948, "M4A4 | Evil Daimyo": 3.10989, "MP9 | Ruby Poison Dart": 1.3361, "Negev | Loudmouth": 2.6847975, "P2000 | Handgun": 1.06833, "CZ75-Auto | Yellow Jacket": 6.61346, "MP7 | Nemesis": 9.624183333333333, "SG 553 | Cyrex": 6.994500000000001, "AK-47 | Aquamarine Revenge": 51.55119, "AWP | Hyper Beast": 55.36155000000001, "Falchion Knife | Fade": 486.96775, "Falchion Knife | Case Hardened": 266.01867000000004, "Falchion Knife | Slaughter": 353.50970333333333, "Falchion Knife | Crimson Web": 307.48007, "Falchion Knife | Boreal Forest": 148.62360999999999, "Falchion Knife | Blue Steel": 195.94355, "Falchion Knife | Forest DDPAT": 141.12184, "Falchion Knife | Night": 187.88369000000003, "Falchion Knife | Scorched": 146.25405000000003, "Falchion Knife | Safari Mesh": 134.86472, "Falchion Knife | Urban Masked": 143.1296, "Falchion Knife | Stained": 150.8644}}, {"name": "Shadow Case", "cost": 1.05, "predict_cost": 2.1454307187301245, "difference": 104.32673511715471, "total_return": 2.071408699177792, "profitability_ratio": 58.51437003327096, "roi": -41.485629966729036, "average_prices": {"Dual Berettas | Dualing Dragons": 0.46479000000000004, "FAMAS | Survivor Z": 0.37877000000000005, "Glock-18 | Wraiths": 0.41417000000000004, "MAC-10 | Rangeen": 0.32257, "MAG-7 | Cobalt Core": 0.31255999999999995, "SCAR-20 | Green Marine": 0.26359, "XM1014 | Scumbria": 0.27543999999999996, "Galil AR | Stone Cold": 2.42216, "M249 | Nebula Crusader": 1.83676, "MP7 | Special Delivery": 1.8261400000000003, "P250 | Wingshot": 1.95719, "AK-47 | Frontside Misty": 27.569390000000006, "G3SG1 | Flux": 9.60837, "SSG 08 | Big Iron": 10.184349999999998, "M4A1-S | Golden Coil": 75.83875, "USP-S | Kill Confirmed": 86.82159, "Shadow Daggers | Fade": 439.723725, "Shadow Daggers | Case Hardened": 198.44833000000003, "Shadow Daggers | Crimson Web": 230.76470999999998, "Shadow Daggers | Slaughter": 258.12155333333334, "Shadow Daggers | Safari Mesh": 112.84887000000002, "Shadow Daggers | Stained": 114.92384000000001, "Shadow Daggers | Blue Steel": 139.75179, "Shadow Daggers | Scorched": 118.22427, "Shadow Daggers | Urban Masked": 129.00325, "Shadow Daggers | Night": 122.23983000000003, "Shadow Daggers | Forest DDPAT": 118.38110000000002, "Shadow Daggers | Boreal Forest": 117.91108000000001}}, {"name": "Revolver Case", "cost": 1.67, "predict_cost": 2.3485497548014633, "difference": 40.63172184439901, "total_return": 2.15367370100212, "profitability_ratio": 51.77100242793558, "roi": -48.22899757206443, "average_prices": {"M4A4 | Royal Paladin": 25.164050000000003, "R8 Revolver | Fade": 12.266910000000001, "G3SG1 | The Executioner": 6.399640000000001, "AK-47 | Point Disarray": 19.334910000000004, "P90 | Shapewood": 3.4551800000000004, "Negev | Power Loader": 1.88382, "SG 553 | Tiger Moth": 1.1260299999999999, "Tec-9 | Avalanche": 1.4016900000000003, "PP-Bizon | Fuel Rod": 1.24218, "Five-SeveN | Retrobution": 1.1989, "XM1014 | Teclu Burner": 1.17011, "R8 Revolver | Crimson Web": 0.45403, "Desert Eagle | Corinthian": 1.01857, "AUG | Ricochet": 0.29737, "P2000 | Imperial": 0.34424333333333335, "Sawed-Off | Yorick": 0.17004, "SCAR-20 | Outbreak": 0.19098, "Bayonet | Fade": 940.775245, "Bayonet | Slaughter": 762.1189833333333, "Bayonet | Case Hardened": 579.0264300000001, "Bayonet | Night": 386.86725, "Bayonet | Crimson Web": 495.44675000000007, "Bayonet | Blue Steel": 498.7956, "Bayonet | Stained": 406.29424000000006, "Bayonet | Safari Mesh": 327.78502000000003, "Bayonet | Urban Masked": 343.15517000000006, "Bayonet | Scorched": 325.42941, "Bayonet | Forest DDPAT": 300.09444, "Bayonet | Boreal Forest": 327.84270000000004, "Flip Knife | Fade": 1045.9882, "Flip Knife | Crimson Web": 295.63783, "Flip Knife | Slaughter": 556.7705, "Flip Knife | Case Hardened": 350.51495000000006, "Flip Knife | Night": 279.13901999999996, "Flip Knife | Stained": 253.81400000000002, "Flip Knife | Blue Steel": 290.21262, "Flip Knife | Forest DDPAT": 225.43328999999997, "Flip Knife | Scorched": 212.70335000000003, "Flip Knife | Safari Mesh": 211.25877, "Flip Knife | Boreal Forest": 220.27391000000003, "Flip Knife | Urban Masked": 218.21346000000003, "Gut Knife | Crimson Web": 181.61738, "Gut Knife | Fade": 309.73177000000004, "Gut Knife | Case Hardened": 226.46593000000004, "Gut Knife | Blue Steel": 155.4466, "Gut Knife | Night": 132.91708, "Gut Knife | Slaughter": 223.82513999999998, "Gut Knife | Boreal Forest": 123.87463000000002, "Gut Knife | Forest DDPAT": 124.19846000000001, "Gut Knife | Stained": 141.91458, "Gut Knife | Urban Masked": 131.83136000000002, "Gut Knife | Safari Mesh": 128.94198, "Gut Knife | Scorched": 126.73970999999997, "Karambit | Fade": 1639.2760000000003, "Karambit | Slaughter": 1297.1049666666665, "Karambit | Crimson Web": 1155.81128, "Karambit | Case Hardened": 1045.51831, "Karambit | Blue Steel": 943.27921, "Karambit | Stained": 856.75436, "Karambit | Night": 547.56663, "Karambit | Boreal Forest": 592.95549, "Karambit | Forest DDPAT": 590.7430300000001, "Karambit | Urban Masked": 684.7818800000001}}, {"name": "Operation Wildfire Case", "cost": 1.85, "predict_cost": 4.246066577868095, "difference": 129.5171123171943, "total_return": 2.9221847570335417, "profitability_ratio": 67.33144601459774, "roi": -32.66855398540226, "average_prices": {"USP-S | Lead Conduit": 0.8717599999999999, "Tec-9 | Jambiya": 0.39132000000000006, "SSG 08 | Necropos": 0.48496, "MAC-10 | Lapis Gator": 0.45065000000000005, "Dual Berettas | Cartel": 0.41683, "PP-Bizon | Photic Zone": 0.5127200000000001, "MP7 | Impire": 2.6902299999999997, "MAG-7 | Praetorian": 2.4834799999999997, "Glock-18 | Royal Legion": 2.6051000000000006, "Five-SeveN | Triumvirate": 2.3129600000000003, "FAMAS | Valence": 2.84523, "Nova | Hyper Beast": 17.430349999999997, "Desert Eagle | Kumicho Dragon": 22.87433, "AWP | Elite Build": 17.84815, "M4A4 | The Battlestar": 9.22192, "AK-47 | Fuel Injector": 243.55509999999998, "Bowie Knife | Fade": 720.681815, "Bowie Knife | Slaughter": 410.39315000000005, "Bowie Knife | Crimson Web": 296.34958000000006, "Bowie Knife | Case Hardened": 326.67492000000004, "Bowie Knife | Night": 201.20745000000002, "Bowie Knife | Stained": 196.73791999999997, "Bowie Knife | Blue Steel": 211.42236, "Bowie Knife | Safari Mesh": 150.48725000000002, "Bowie Knife | Scorched": 139.03166, "Bowie Knife | Boreal Forest": 154.02633, "Bowie Knife | Urban Masked": 149.68884000000006, "Bowie Knife | Forest DDPAT": 159.22626}}, {"name": "Chroma 3 Case", "cost": 1.91, "predict_cost": 2.9610486325214316, "difference": 55.028724215781764, "total_return": 2.4017411508463336, "profitability_ratio": 54.585026155598484, "roi": -45.414973844401516, "average_prices": {"Dual Berettas | Ventilators": 0.17526, "G3SG1 | Orange Crash": 0.13545, "M249 | Spectre": 0.15061000000000002, "MP9 | Bioleak": 0.21207, "P2000 | Oceanic": 0.16119999999999998, "Sawed-Off | Fubar": 0.10256000000000001, "SG 553 | Atlas": 0.12783000000000003, "CZ75-Auto | Red Astor": 0.62968, "Galil AR | Firefight": 0.64484, "SSG 08 | Ghost Crusader": 0.9672299999999999, "Tec-9 | Re-Entry": 0.7770700000000001, "XM1014 | Black Tie": 0.71501, "AUG | Fleet Flock": 3.43099, "P250 | Asiimov": 10.0049625, "UMP-45 | Primal Saber": 4.0200000000000005, "PP-Bizon | Judgement of Anubis": 7.61816, "M4A1-S | Chantico's Fire": 39.57445000000001, "Bayonet | Marble Fade": 1267.5693750000003, "Bayonet | Tiger Tooth": 874.10804, "Bayonet | Doppler": 1046.49116, "Bayonet | Rust Coat": 408.12614, "Bayonet | Damascus Steel": 475.17399, "Bayonet | Ultraviolet": 395.75064000000003, "Flip Knife | Marble Fade": 813.4687700000001, "Flip Knife | Tiger Tooth": 694.683315, "Flip Knife | Doppler": 660.472695, "Flip Knife | Ultraviolet": 312.68095, "Flip Knife | Damascus Steel": 289.62934, "Flip Knife | Rust Coat": 279.49622, "Gut Knife | Doppler": 279.918005, "Gut Knife | Ultraviolet": 142.20686000000003, "Gut Knife | Marble Fade": 238.581835, "Gut Knife | Tiger Tooth": 231.88279, "Gut Knife | Damascus Steel": 163.27633, "Gut Knife | Rust Coat": 133.35420000000002, "Karambit | Marble Fade": 1422.182575, "Karambit | Tiger Tooth": 1550.0703750000002, "Karambit | Doppler": 1396.00261, "Karambit | Damascus Steel": 1001.00277, "Karambit | Ultraviolet": 931.37674, "Karambit | Rust Coat": 677.2980000000001, "M9 Bayonet | Marble Fade": 763.6561450000002, "M9 Bayonet | Doppler": 1271.5573450000002, "M9 Bayonet | Tiger Tooth": 1725.0533099999998, "M9 Bayonet | Damascus Steel": 757.3922600000002, "M9 Bayonet | Ultraviolet": 650.58983, "M9 Bayonet | Rust Coat": 541.52038}}, {"name": "Gamma Case", "cost": 2.11, "predict_cost": 3.3276662769700076, "difference": 57.70930222606672, "total_return": 2.5502245316890835, "profitability_ratio": 55.43966373237138, "roi": -44.560336267628614, "average_prices": {"Five-SeveN | Violent Daimyo": 0.27194, "MAC-10 | Carnivore": 0.17246, "Nova | Exo": 0.23535, "P250 | Iron Clad": 0.22490000000000002, "PP-Bizon | Harvester": 0.17744000000000001, "SG 553 | Aerial": 0.17831, "Tec-9 | Ice Cap": 0.28234000000000004, "AUG | Aristocrat": 1.04879, "AWP | Phobos": 2.77538, "P90 | Chopper": 1.0576299999999998, "R8 Revolver | Reboot": 1.00596, "Sawed-Off | Limelight": 0.80782, "M4A4 | Desolate Space": 11.41867, "P2000 | Imperial Dragon": 4.3727599999999995, "SCAR-20 | Bloodsport": 4.55395, "Glock-18 | Wasteland Rebel": 7.990360000000002, "M4A1-S | Mecha Industries": 38.130469999999995, "Bayonet | Lore": 800.9128400000002, "Bayonet | Gamma Doppler": 1024.69833, "Bayonet | Autotronic": 809.66415, "Bayonet | Bright Water": 431.03129, "Bayonet | Black Laminate": 533.1360099999999, "Bayonet | Freehand": 506.0562, "Flip Knife | Lore": 532.64649, "Flip Knife | Gamma Doppler": 890.474245, "Flip Knife | Bright Water": 280.82249, "Flip Knife | Autotronic": 458.15098, "Flip Knife | Freehand": 292.46650999999997, "Flip Knife | Black Laminate": 343.98872000000006, "Gut Knife | Lore": 264.79917, "Gut Knife | Autotronic": 273.21840000000003, "Gut Knife | Gamma Doppler": 324.62760499999996, "Gut Knife | Bright Water": 155.78078000000005, "Gut Knife | Black Laminate": 178.78310000000002, "Gut Knife | Freehand": 156.80367000000004, "Karambit | Autotronic": 1334.4099700000004, "Karambit | Gamma Doppler": 1502.5597050000001, "Karambit | Lore": 1350.6087300000002, "Karambit | Black Laminate": 807.6472100000001, "Karambit | Freehand": 907.08456, "Karambit | Bright Water": 788.53002, "M9 Bayonet | Autotronic": 1168.0043799999999, "M9 Bayonet | Gamma Doppler": 1302.4968000000001, "M9 Bayonet | Lore": 1156.62909, "M9 Bayonet | Black Laminate": 983.61401, "M9 Bayonet | Freehand": 725.8863000000001, "M9 Bayonet | Bright Water": 779.2461500000001}}, {"name": "Gamma 2 Case", "cost": 2.14, "predict_cost": 2.748866743776639, "difference": 28.451716998908356, "total_return": 2.3158056137234166, "profitability_ratio": 50.01739986443664, "roi": -49.98260013556337, "average_prices": {"CZ75-Auto | Imprint": 0.13445, "Five-SeveN | Scumbria": 0.13474000000000003, "G3SG1 | Ventilator": 0.15789000000000003, "Negev | Dazzle": 0.19877000000000003, "P90 | Grim": 0.3398500000000001, "UMP-45 | Briefing": 0.12825999999999999, "XM1014 | Slipstream": 0.15001, "Desert Eagle | Directive": 1.2899699999999998, "Glock-18 | Weasel": 0.90718, "MAG-7 | Petroglyph": 0.6412, "SCAR-20 | Powercore": 0.5719399999999999, "SG 553 | Triarch": 0.5875, "AUG | Syd Mead": 3.5381400000000007, "MP9 | Airlock": 3.32811, "Tec-9 | Fuel Injector": 4.3469299999999995, "AK-47 | Neon Revolution": 35.08571, "FAMAS | Roll Cage": 5.79782, "Bayonet | Lore": 800.9128400000002, "Bayonet | Gamma Doppler": 1024.69833, "Bayonet | Autotronic": 809.66415, "Bayonet | Bright Water": 431.03129, "Bayonet | Black Laminate": 533.1360099999999, "Bayonet | Freehand": 506.0562, "Flip Knife | Lore": 532.64649, "Flip Knife | Gamma Doppler": 890.474245, "Flip Knife | Bright Water": 280.82249, "Flip Knife | Autotronic": 458.15098, "Flip Knife | Freehand": 292.46650999999997, "Flip Knife | Black Laminate": 343.98872000000006, "Gut Knife | Lore": 264.79917, "Gut Knife | Autotronic": 273.21840000000003, "Gut Knife | Gamma Doppler": 324.62760499999996, "Gut Knife | Bright Water": 155.78078000000005, "Gut Knife | Black Laminate": 178.78310000000002, "Gut Knife | Freehand": 156.80367000000004, "Karambit | Autotronic": 1334.4099700000004, "Karambit | Gamma Doppler": 1502.5597050000001, "Karambit | Lore": 1350.6087300000002, "Karambit | Black Laminate": 807.6472100000001, "Karambit | Freehand": 907.08456, "Karambit | Bright Water": 788.53002, "M9 Bayonet | Autotronic": 1168.0043799999999, "M9 Bayonet | Gamma Doppler": 1302.4968000000001, "M9 Bayonet | Lore": 1156.62909, "M9 Bayonet | Black Laminate": 983.61401, "M9 Bayonet | Freehand": 725.8863000000001, "M9 Bayonet | Bright Water": 779.2461500000001}}, {"name": "Glove Case", "cost": 4.16, "predict_cost": 1.3380083601902202, "difference": -67.8363374954274, "total_return": 1.7443955196993333, "profitability_ratio": 26.231511574426065, "roi": -73.76848842557393, "average_prices": {"CZ75-Auto | Polymer": 0.19662000000000002, "Glock-18 | Ironwork": 0.34168000000000004, "MP7 | Cirrus": 0.39454, "Galil AR | Black Sand": 0.21095000000000003, "MP9 | Sand Scale": 0.22342, "MAG-7 | Sonar": 0.21593000000000004, "P2000 | Turf": 0.23445, "Dual Berettas | Royal Consorts": 0.9221199999999999, "G3SG1 | Stinger": 0.7911400000000001, "M4A1-S | Flashback": 1.6492300000000002, "Nova | Gila": 0.93094, "USP-S | Cyrex": 2.8036800000000004, "FAMAS | Mecha Industries": 4.631349999999999, "P90 | Shallow Grave": 3.43789, "Sawed-Off | Wasteland Princess": 3.50129, "SSG 08 | Dragonfire": 18.82354, "M4A4 | Buzz Kill": 18.17714, "Bloodhound Gloves | Snakebite": 136.65888, "Bloodhound Gloves | Charred": 157.25097, "Bloodhound Gloves | Bronzed": 114.73857000000001, "Bloodhound Gloves | Guerrilla": 110.94624, "Driver Gloves | Crimson Weave": 519.75396, "Driver Gloves | Diamondback": 243.84258, "Driver Gloves | Lunar Weave": 287.3466, "Driver Gloves | Convoy": 117.59085, "Hand Wraps | Slaughter": 352.77975000000004, "Hand Wraps | Badlands": 175.04109000000003, "Hand Wraps | Leather": 225.17361, "Hand Wraps | Spruce DDPAT": 139.19049, "Moto Gloves | Spearmint": 835.5787200000001, "Moto Gloves | Cool Mint": 480.66624, "Moto Gloves | Boom!": 272.64195, "Moto Gloves | Eclipse": 217.55853, "Specialist Gloves | Crimson Kimono": 890.71308, "Specialist Gloves | Emerald Web": 880.2142200000002, "Specialist Gloves | Foundation": 477.64197, "Specialist Gloves | Forest DDPAT": 175.20740999999998, "Sport Gloves | Pandora's Box": 748.4745600000001, "Sport Gloves | Superconductor": 622.22679, "Sport Gloves | Hedge Maze": 1115.19702, "Sport Gloves | Arid": 729.5191199999999}}, {"name": "Spectrum Case", "cost": 2.31, "predict_cost": 3.3963472443096467, "difference": 47.02801923418384, "total_return": 2.578040929466334, "profitability_ratio": 53.709186030548615, "roi": -46.29081396945139, "average_prices": {"PP-Bizon | Jungle Slipstream": 0.19036000000000003, "SCAR-20 | Blueprint": 0.20083000000000004, "Desert Eagle | Oxide Blaze": 0.47099, "Five-SeveN | Capillary": 0.20899000000000006, "MP7 | Akoben": 0.19007000000000002, "P250 | Ripple": 0.19901000000000002, "Sawed-Off | Zander": 0.17371, "Galil AR | Crimson Tsunami": 1.4647600000000003, "M249 | Emerald Poison Dart": 1.50633, "MAC-10 | Last Dive": 1.57593, "UMP-45 | Scaffold": 1.44926, "XM1014 | Seasons": 1.48058, "AWP | Fever Dream": 11.322480000000002, "CZ75-Auto | Xiangliu": 9.7518, "M4A1-S | Decimator": 17.18545, "AK-47 | Bloodsport": 126.7222, "USP-S | Neo-Noir": 29.569780000000005, "Bowie Knife | Marble Fade": 496.71342500000003, "Bowie Knife | Doppler": 571.58069, "Bowie Knife | Tiger Tooth": 438.50146500000005, "Bowie Knife | Damascus Steel": 223.37675000000002, "Bowie Knife | Ultraviolet": 199.59449000000004, "Bowie Knife | Rust Coat": 167.98070000000004, "Butterfly Knife | Marble Fade": 1712.80841, "Butterfly Knife | Doppler": 1512.156625, "Butterfly Knife | Tiger Tooth": 708.8006400000002, "Butterfly Knife | Damascus Steel": 905.3235900000001, "Butterfly Knife | Ultraviolet": 1061.3361000000002, "Butterfly Knife | Rust Coat": 1015.3260600000002, "Falchion Knife | Doppler": 569.4767800000001, "Falchion Knife | Marble Fade": 434.754575, "Falchion Knife | Tiger Tooth": 410.48303000000004, "Falchion Knife | Ultraviolet": 181.92955, "Falchion Knife | Damascus Steel": 231.92643, "Falchion Knife | Rust Coat": 146.54318, "Huntsman Knife | Marble Fade": 538.6923850000001, "Huntsman Knife | Doppler": 465.431065, "Huntsman Knife | Tiger Tooth": 457.87093500000003, "Huntsman Knife | Ultraviolet": 199.98298000000003, "Huntsman Knife | Damascus Steel": 229.35266000000001, "Huntsman Knife | Rust Coat": 169.44372, "Shadow Daggers | Doppler": 451.56396, "Shadow Daggers | Marble Fade": 362.53678500000007, "Shadow Daggers | Tiger Tooth": 300.65489, "Shadow Daggers | Damascus Steel": 152.96056, "Shadow Daggers | Ultraviolet": 156.37169, "Shadow Daggers | Rust Coat": 131.5917}}, {"name": "Operation Hydra Case", "cost": 19.8, "predict_cost": 18.675648165824775, "difference": -5.678544617046595, "total_return": 8.766292619186999, "profitability_ratio": 39.3283652722611, "roi": -60.6716347277389, "average_prices": {"USP-S | Blueprint": 12.04174, "FAMAS | Macabre": 2.3781, "M4A1-S | Briefing": 4.9346000000000005, "MAC-10 | Aloha": 2.3291200000000005, "MAG-7 | Hard Water": 2.2440299999999995, "Tec-9 | Cut Out": 2.5425300000000006, "UMP-45 | Metal Flowers": 2.0205800000000003, "AK-47 | Orbit Mk01": 17.71539, "P2000 | Woodsman": 7.6334100000000005, "P250 | Red Rock": 7.133310000000001, "P90 | Death Grip": 7.3591, "SSG 08 | Death's Head": 7.54061, "Dual Berettas | Cobra Strike": 46.643950000000004, "Galil AR | Sugar Rush": 45.633810000000004, "M4A4 | Hellfire": 54.27536, "Five-SeveN | Hyper Beast": 38.99254, "AWP | Oni Taiji": 389.05538000000007, "Bloodhound Gloves | Snakebite": 136.65888, "Bloodhound Gloves | Charred": 157.25097, "Bloodhound Gloves | Bronzed": 114.73857000000001, "Bloodhound Gloves | Guerrilla": 110.94624, "Driver Gloves | Crimson Weave": 519.75396, "Driver Gloves | Diamondback": 243.84258, "Driver Gloves | Lunar Weave": 287.3466, "Driver Gloves | Convoy": 117.59085, "Hand Wraps | Slaughter": 352.77975000000004, "Hand Wraps | Badlands": 175.04109000000003, "Hand Wraps | Leather": 225.17361, "Hand Wraps | Spruce DDPAT": 139.19049, "Moto Gloves | Spearmint": 835.5787200000001, "Moto Gloves | Cool Mint": 480.66624, "Moto Gloves | Boom!": 272.64195, "Moto Gloves | Eclipse": 217.55853, "Specialist Gloves | Crimson Kimono": 890.71308, "Specialist Gloves | Emerald Web": 880.2142200000002, "Specialist Gloves | Foundation": 477.64197, "Specialist Gloves | Forest DDPAT": 175.20740999999998, "Sport Gloves | Pandora's Box": 748.4745600000001, "Sport Gloves | Superconductor": 622.22679, "Sport Gloves | Hedge Maze": 1115.19702, "Sport Gloves | Arid": 729.5191199999999}}, {"name": "Spectrum 2 Case", "cost": 1.59, "predict_cost": 1.5960052803116396, "difference": 0.37769058563770397, "total_return": 1.8488865487775001, "profitability_ratio": 45.31584678376226, "roi": -54.68415321623774, "average_prices": {"AK-47 | The Empress": 55.07167999999999, "P250 | See Ya Later": 6.6049299999999995, "M4A1-S | Leaded Glass": 7.84863, "PP-Bizon | High Roller": 4.32665, "R8 Revolver | Llama Cannon": 3.9959800000000003, "SG 553 | Phantom": 0.6866099999999999, "CZ75-Auto | Tacticat": 0.7151899999999999, "MP9 | Goo": 0.8105500000000002, "UMP-45 | Exposure": 0.7454700000000001, "XM1014 | Ziggy": 0.6937899999999999, "Glock-18 | Off World": 0.21668, "AUG | Triqua": 0.14402, "MAC-10 | Oceanic": 0.14716, "Tec-9 | Cracked Opal": 0.13951000000000002, "Sawed-Off | Morris": 0.12746000000000002, "G3SG1 | Hunter": 0.12657000000000002, "SCAR-20 | Jungle Slipstream": 0.12824, "Bowie Knife | Marble Fade": 496.71342500000003, "Bowie Knife | Doppler": 571.58069, "Bowie Knife | Tiger Tooth": 438.50146500000005, "Bowie Knife | Damascus Steel": 223.37675000000002, "Bowie Knife | Ultraviolet": 199.59449000000004, "Bowie Knife | Rust Coat": 167.98070000000004, "Butterfly Knife | Marble Fade": 1712.80841, "Butterfly Knife | Doppler": 1512.156625, "Butterfly Knife | Tiger Tooth": 708.8006400000002, "Butterfly Knife | Damascus Steel": 905.3235900000001, "Butterfly Knife | Ultraviolet": 1061.3361000000002, "Butterfly Knife | Rust Coat": 1015.3260600000002, "Falchion Knife | Doppler": 569.4767800000001, "Falchion Knife | Marble Fade": 434.754575, "Falchion Knife | Tiger Tooth": 410.48303000000004, "Falchion Knife | Ultraviolet": 181.92955, "Falchion Knife | Damascus Steel": 231.92643, "Falchion Knife | Rust Coat": 146.54318, "Huntsman Knife | Marble Fade": 538.6923850000001, "Huntsman Knife | Doppler": 465.431065, "Huntsman Knife | Tiger Tooth": 457.87093500000003, "Huntsman Knife | Ultraviolet": 199.98298000000003, "Huntsman Knife | Damascus Steel": 229.35266000000001, "Huntsman Knife | Rust Coat": 169.44372, "Shadow Daggers | Doppler": 451.56396, "Shadow Daggers | Marble Fade": 362.53678500000007, "Shadow Daggers | Tiger Tooth": 300.65489, "Shadow Daggers | Damascus Steel": 152.96056, "Shadow Daggers | Ultraviolet": 156.37169, "Shadow Daggers | Rust Coat": 131.5917}}, {"name": "Clutch Case", "cost": 0.91, "predict_cost": 0.517823298702778, "difference": -43.09634080189253, "total_return": 1.4122133329157502, "profitability_ratio": 41.53568626222794, "roi": -58.46431373777206, "average_prices": {"M4A4 | Neo-Noir": 12.49022, "MP7 | Bloodsport": 2.9704900000000003, "USP-S | Cortex": 4.15296, "AWP | Mortis": 4.03882, "AUG | Stymphalian": 3.1706, "Glock-18 | Moonrise": 0.72019, "UMP-45 | Arctic Wolf": 0.58731, "MAG-7 | SWAG-7": 0.57068, "Negev | Lionfish": 0.5742, "Nova | Wild Six": 0.56369, "SG 553 | Aloha": 0.12584, "MP9 | Black Sand": 0.12822, "R8 Revolver | Grip": 0.12209, "Five-SeveN | Flame Test": 0.13085000000000002, "P2000 | Urban Hazard": 0.12164, "PP-Bizon | Night Riot": 0.12299000000000002, "XM1014 | Oxide Blaze": 0.12272999999999999, "Driver Gloves | King Snake": 739.54728, "Driver Gloves | Imperial Plaid": 589.28418, "Driver Gloves | Overtake": 200.38464000000005, "Driver Gloves | Racing Green": 79.93070999999999, "Hand Wraps | Cobalt Skulls": 597.03696, "Hand Wraps | Overprint": 388.20896999999997, "Hand Wraps | Duct Tape": 95.51357999999999, "Hand Wraps | Arboreal": 126.81009, "Hydra Gloves | Case Hardened": 138.05667, "Hydra Gloves | Emerald": 101.71215000000001, "Hydra Gloves | Mangrove": 80.06472, "Hydra Gloves | Rattler": 86.70402, "Moto Gloves | POW!": 568.78596, "Moto Gloves | Polygon": 302.0976, "Moto Gloves | Turtle": 315.98055, "Moto Gloves | Transport": 146.78793000000002, "Specialist Gloves | Fade": 615.25386, "Specialist Gloves | Crimson Web": 462.65652, "Specialist Gloves | Mogul": 356.04801000000003, "Specialist Gloves | Buckshot": 115.02333000000002, "Sport Gloves | Vice": 1476.6886800000002, "Sport Gloves | Amphibious": 1063.4891400000001, "Sport Gloves | Omega": 876.5034300000002, "Sport Gloves | Bronze Morph": 288.11592}}, {"name": "Horizon Case", "cost": 0.84, "predict_cost": 1.9698857571892638, "difference": 134.5102091891981, "total_return": 2.0003114408374243, "profitability_ratio": 60.069412637760486, "roi": -39.930587362239514, "average_prices": {"AK-47 | Neon Rider": 68.58042, "Desert Eagle | Code Red": 37.71748000000001, "M4A1-S | Nightmare": 16.833969999999997, "Sawed-Off | Devourer": 5.591119999999999, "FAMAS | Eye of Athena": 5.741910000000001, "AWP | PAW": 3.00357, "CZ75-Auto | Eco": 1.1294600000000001, "MP7 | Powercore": 1.06592, "Nova | Toy Soldier": 1.04301, "G3SG1 | High Seas": 1.0527199999999999, "Glock-18 | Warhawk": 0.28114, "P90 | Traction": 0.21774000000000002, "MP9 | Capillary": 0.22896, "Tec-9 | Snek-9": 0.19438000000000002, "AUG | Amber Slipstream": 0.2084, "Dual Berettas | Shred": 0.22143000000000004, "R8 Revolver | Survivalist": 0.19570000000000004, "Navaja Knife | Crimson Web": 154.79276, "Navaja Knife | Fade": 310.50667500000003, "Navaja Knife | Slaughter": 194.05328999999998, "Navaja Knife | Case Hardened": 162.27429000000004, "Navaja Knife | Blue Steel": 114.68428, "Navaja Knife | Stained": 111.13402000000002, "Navaja Knife | Night Stripe": 111.15963, "Navaja Knife | Scorched": 108.97494, "Navaja Knife | Boreal Forest": 102.80782, "Navaja Knife | Safari Mesh": 102.82157000000001, "Navaja Knife | Forest DDPAT": 112.40889000000001, "Navaja Knife | Urban Masked": 104.16982000000002, "Stiletto Knife | Fade": 1031.00068, "Stiletto Knife | Crimson Web": 569.3756000000001, "Stiletto Knife | Slaughter": 625.9745866666666, "Stiletto Knife | Case Hardened": 468.5486900000001, "Stiletto Knife | Blue Steel": 364.20213000000007, "Stiletto Knife | Scorched": 220.94414999999998, "Stiletto Knife | Safari Mesh": 216.81113, "Stiletto Knife | Stained": 348.72299000000004, "Stiletto Knife | Night Stripe": 269.35765999999995, "Stiletto Knife | Boreal Forest": 244.01105, "Stiletto Knife | Urban Masked": 258.93137, "Stiletto Knife | Forest DDPAT": 231.15408, "Talon Knife | Fade": 1599.498095, "Talon Knife | Slaughter": 980.2650000000001, "Talon Knife | Case Hardened": 774.8195900000001, "Talon Knife | Stained": 501.47729, "Talon Knife | Crimson Web": 660.5443300000001, "Talon Knife | Blue Steel": 611.1873, "Talon Knife | Safari Mesh": 387.78836, "Talon Knife | Night Stripe": 401.72233000000006, "Talon Knife | Scorched": 401.48402, "Talon Knife | Forest DDPAT": 390.4584400000001, "Talon Knife | Boreal Forest": 342.20243999999997, "Talon Knife | Urban Masked": 389.64664, "Ursus Knife | Fade": 641.658405, "Ursus Knife | Crimson Web": 450.34616, "Ursus Knife | Slaughter": 524.89444, "Ursus Knife | Case Hardened": 304.9405, "Ursus Knife | Night Stripe": 206.60033, "Ursus Knife | Blue Steel": 254.60849000000002, "Ursus Knife | Boreal Forest": 172.94731000000002, "Ursus Knife | Stained": 195.31973000000002, "Ursus Knife | Urban Masked": 184.47346000000002, "Ursus Knife | Forest DDPAT": 178.50209000000004}}, {"name": "Danger Zone Case", "cost": 0.69, "predict_cost": 1.314558351252872, "difference": 90.5157030801264, "total_return": 1.7348980591691743, "profitability_ratio": 54.556542741169004, "roi": -45.443457258830996, "average_prices": {"AK-47 | Asiimov": 60.226980000000005, "AWP | Neo-Noir": 37.96356, "Desert Eagle | Mecha Industries": 6.53841, "MP5-SD | Phosphor": 5.28562, "UMP-45 | Momentum": 5.2724, "USP-S | Flashback": 1.01091, "P250 | Nevermore": 0.9386899999999999, "Galil AR | Signal": 0.8024000000000001, "MAC-10 | Pipe Down": 0.73217, "G3SG1 | Scavenger": 0.7219599999999998, "M4A4 | Magnesium": 0.28083, "Glock-18 | Oxide Blaze": 0.15492999999999998, "Tec-9 | Fubar": 0.39793750000000006, "SG 553 | Danger Close": 0.12660000000000002, "MP9 | Modest Threat": 0.13926000000000002, "Sawed-Off | Black Sand": 0.12107000000000002, "Nova | Wood Fired": 0.12758, "Navaja Knife | Crimson Web": 154.79276, "Navaja Knife | Fade": 310.50667500000003, "Navaja Knife | Slaughter": 194.05328999999998, "Navaja Knife | Case Hardened": 162.27429000000004, "Navaja Knife | Blue Steel": 114.68428, "Navaja Knife | Stained": 111.13402000000002, "Navaja Knife | Night Stripe": 111.15963, "Navaja Knife | Scorched": 108.97494, "Navaja Knife | Boreal Forest": 102.80782, "Navaja Knife | Safari Mesh": 102.82157000000001, "Navaja Knife | Forest DDPAT": 112.40889000000001, "Navaja Knife | Urban Masked": 104.16982000000002, "Stiletto Knife | Fade": 1031.00068, "Stiletto Knife | Crimson Web": 569.3756000000001, "Stiletto Knife | Slaughter": 625.9745866666666, "Stiletto Knife | Case Hardened": 468.5486900000001, "Stiletto Knife | Blue Steel": 364.20213000000007, "Stiletto Knife | Scorched": 220.94414999999998, "Stiletto Knife | Safari Mesh": 216.81113, "Stiletto Knife | Stained": 348.72299000000004, "Stiletto Knife | Night Stripe": 269.35765999999995, "Stiletto Knife | Boreal Forest": 244.01105, "Stiletto Knife | Urban Masked": 258.93137, "Stiletto Knife | Forest DDPAT": 231.15408, "Talon Knife | Fade": 1599.498095, "Talon Knife | Slaughter": 980.2650000000001, "Talon Knife | Case Hardened": 774.8195900000001, "Talon Knife | Stained": 501.47729, "Talon Knife | Crimson Web": 660.5443300000001, "Talon Knife | Blue Steel": 611.1873, "Talon Knife | Safari Mesh": 387.78836, "Talon Knife | Night Stripe": 401.72233000000006, "Talon Knife | Scorched": 401.48402, "Talon Knife | Forest DDPAT": 390.4584400000001, "Talon Knife | Boreal Forest": 342.20243999999997, "Talon Knife | Urban Masked": 389.64664, "Ursus Knife | Fade": 641.658405, "Ursus Knife | Crimson Web": 450.34616, "Ursus Knife | Slaughter": 524.89444, "Ursus Knife | Case Hardened": 304.9405, "Ursus Knife | Night Stripe": 206.60033, "Ursus Knife | Blue Steel": 254.60849000000002, "Ursus Knife | Boreal Forest": 172.94731000000002, "Ursus Knife | Stained": 195.31973000000002, "Ursus Knife | Urban Masked": 184.47346000000002, "Ursus Knife | Forest DDPAT": 178.50209000000004}}, {"name": "Prisma Case", "cost": 0.88, "predict_cost": 2.487187299266049, "difference": 182.63492037114193, "total_return": 2.209823129774979, "profitability_ratio": 65.57338664020709, "roi": -34.42661335979291, "average_prices": {"M4A4 | The Emperor": 39.325810000000004, "Five-SeveN | Angry Mob": 5.959600000000001, "AUG | Momentum": 4.9339200000000005, "XM1014 | Incinegator": 6.202472500000001, "R8 Revolver | Skull Crusher": 2.1504100000000004, "AWP | Atheris": 5.73701, "Desert Eagle | Light Rail": 1.66269, "UMP-45 | Moonrise": 0.75188, "Tec-9 | Bamboozle": 0.6170800000000001, "MP5-SD | Gauss": 0.53718, "AK-47 | Uncharted": 0.97938, "P90 | Off World": 0.28657, "P250 | Verdigris": 0.28629, "FAMAS | Crypsis": 0.28803000000000006, "MAC-10 | Whitefish": 0.26747000000000004, "Galil AR | Akoben": 0.32055, "MP7 | Mischief": 0.2919725, "Navaja Knife | Doppler": 293.594035, "Navaja Knife | Tiger Tooth": 234.456145, "Navaja Knife | Marble Fade": 275.462015, "Navaja Knife | Ultraviolet": 130.58382, "Navaja Knife | Damascus Steel": 124.76567, "Navaja Knife | Rust Coat": 117.65772000000001, "Stiletto Knife | Doppler": 790.6543800000001, "Stiletto Knife | Marble Fade": 736.5198449999999, "Stiletto Knife | Tiger Tooth": 719.482925, "Stiletto Knife | Ultraviolet": 340.45763, "Stiletto Knife | Damascus Steel": 356.48976, "Stiletto Knife | Rust Coat": 271.87826000000007, "Talon Knife | Marble Fade": 1149.8428950000002, "Talon Knife | Doppler": 1428.4139349999998, "Talon Knife | Tiger Tooth": 1144.316725, "Talon Knife | Ultraviolet": 449.24179, "Talon Knife | Damascus Steel": 584.60312, "Talon Knife | Rust Coat": 498.19866000000013, "Ursus Knife | Marble Fade": 696.751225, "Ursus Knife | Doppler": 749.2318100000001, "Ursus Knife | Tiger Tooth": 563.43611, "Ursus Knife | Ultraviolet": 258.28488, "Ursus Knife | Damascus Steel": 240.91923000000003, "Ursus Knife | Rust Coat": 188.38542000000004}}, {"name": "CS20 Case", "cost": 0.77, "predict_cost": 1.4257106644392925, "difference": 85.15722914796005, "total_return": 1.7799157267591663, "profitability_ratio": 54.5986419251278, "roi": -45.4013580748722, "average_prices": {"AWP | Wildfire": 94.43998999999998, "FAMAS | Commemoration": 21.06329, "MP9 | Hydra": 6.9695, "AUG | Death by Puppy": 7.86306, "P90 | Nostalgia": 6.83499, "MP5-SD | Agent": 0.96221, "P250 | Inferno": 0.9863300000000002, "UMP-45 | Plastique": 0.9697300000000001, "Five-SeveN | Buddy": 0.9645100000000001, "M249 | Aztec": 0.9066200000000002, "Glock-18 | Sacrifice": 0.3134800000000001, "FAMAS | Decommissioned": 0.15471000000000001, "MAC-10 | Classic Crate": 0.13579, "Dual Berettas | Elite 1.6": 0.16382999999999998, "Tec-9 | Flash Out": 0.14915, "MAG-7 | Popdog": 0.15855999999999998, "SCAR-20 | Assault": 0.13992000000000002, "Classic Knife | Fade": 963.09196, "Classic Knife | Slaughter": 510.04198, "Classic Knife | Crimson Web": 575.51948, "Classic Knife | Case Hardened": 394.09362999999996, "Classic Knife | Night Stripe": 277.5445, "Classic Knife | Scorched": 202.62722000000002, "Classic Knife | Forest DDPAT": 156.67035, "Classic Knife | Blue Steel": 270.44789000000003, "Classic Knife | Stained": 242.34687000000002, "Classic Knife | Boreal Forest": 212.29947, "Classic Knife | Urban Masked": 182.29124999999996, "Classic Knife | Safari Mesh": 178.98786}}, {"name": "Shattered Web Case", "cost": 3.34, "predict_cost": 4.998144364363759, "difference": 49.64504084921434, "total_return": 3.2267828965027174, "profitability_ratio": 55.347905600389666, "roi": -44.652094399610334, "average_prices": {"AWP | Containment Breach": 150.44674, "MAC-10 | Stalker": 23.3051, "SSG 08 | Bloodshot": 24.4365725, "SG 553 | Colony IV": 12.251539999999999, "Tec-9 | Decimator": 16.38806, "AK-47 | Rat Rod": 6.266940000000001, "AUG | Arctic Wolf": 3.0290500000000002, "MP7 | Neon Ply": 1.8339499999999997, "PP-Bizon | Embargo": 1.91172, "P2000 | Obsidian": 1.8257400000000004, "Dual Berettas | Balance": 0.63415, "MP5-SD | Acid Wash": 0.52106, "M249 | Warbird": 0.77932, "R8 Revolver | Memento": 0.59814, "SCAR-20 | Torn": 0.56003, "G3SG1 | Black Sand": 0.5649799999999999, "Nova | Plume": 0.54523, "Nomad Knife | Fade": 1292.1841399999998, "Nomad Knife | Crimson Web": 611.1303700000001, "Nomad Knife | Slaughter": 626.2354066666667, "Nomad Knife | Stained": 347.81132, "Nomad Knife | Case Hardened": 356.64491000000004, "Nomad Knife | Blue Steel": 412.48017000000004, "Nomad Knife | Night Stripe": 242.87602, "Nomad Knife | Forest DDPAT": 207.30187, "Nomad Knife | Scorched": 182.95007, "Nomad Knife | Urban Masked": 227.98375000000001, "Nomad Knife | Boreal Forest": 227.93209000000002, "Nomad Knife | Safari Mesh": 195.95307000000003, "Paracord Knife | Fade": 944.1675150000001, "Paracord Knife | Slaughter": 540.5253033333333, "Paracord Knife | Crimson Web": 403.79298, "Paracord Knife | Blue Steel": 245.97265000000002, "Paracord Knife | Case Hardened": 346.70154, "Paracord Knife | Stained": 212.14702000000003, "Paracord Knife | Boreal Forest": 164.01174, "Paracord Knife | Urban Masked": 156.59925, "Paracord Knife | Night Stripe": 187.75449999999998, "Paracord Knife | Scorched": 155.37471, "Paracord Knife | Forest DDPAT": 152.56409, "Paracord Knife | Safari Mesh": 151.03559, "Skeleton Knife | Slaughter": 1252.4982033333333, "Skeleton Knife | Crimson Web": 1317.21347, "Skeleton Knife | Case Hardened": 878.5411800000003, "Skeleton Knife | Blue Steel": 650.05435, "Skeleton Knife | Urban Masked": 471.0427900000001, "Skeleton Knife | Night Stripe": 503.8573, "Skeleton Knife | Stained": 697.75141, "Skeleton Knife | Forest DDPAT": 407.95366, "Skeleton Knife | Scorched": 419.26128000000006, "Skeleton Knife | Boreal Forest": 382.91046, "Skeleton Knife | Safari Mesh": 388.00128, "Skeleton Knife | Fade": 1690.4928850000001, "Survival Knife | Fade": 721.846705, "Survival Knife | Crimson Web": 479.94479, "Survival Knife | Slaughter": 493.61775666666665, "Survival Knife | Forest DDPAT": 154.11415, "Survival Knife | Case Hardened": 285.66591, "Survival Knife | Blue Steel": 201.06502999999998, "Survival Knife | Night Stripe": 199.48068, "Survival Knife | Urban Masked": 151.57042, "Survival Knife | Stained": 200.84267000000003, "Survival Knife | Boreal Forest": 153.9745}}, {"name": "Prisma 2 Case", "cost": 0.73, "predict_cost": 2.010124784743323, "difference": 175.35955955387988, "total_return": 2.0166086020448124, "profitability_ratio": 62.62759633679541, "roi": -37.37240366320459, "average_prices": {"M4A1-S | Player Two": 40.39786000000001, "Glock-18 | Bullet Queen": 16.289939999999998, "AK-47 | Phantom Disruptor": 9.65569, "MAC-10 | Disco Tech": 5.246320000000001, "MAG-7 | Justice": 3.6889000000000003, "SG 553 | Darkwing": 0.7995899999999999, "SSG 08 | Fever Dream": 1.11626, "Sawed-Off | Apocalypto": 0.7759100000000001, "P2000 | Acid Etched": 0.77096, "SCAR-20 | Enforcer": 0.7623099999999999, "AWP | Capillary": 0.6701400000000001, "Desert Eagle | Blue Ply": 0.31375000000000003, "AUG | Tom Cat": 0.14444, "MP5-SD | Desert Strike": 0.12966000000000003, "CZ75-Auto | Distressed": 0.12837, "Negev | Prototype": 0.12485, "R8 Revolver | Bone Forged": 0.12511, "Navaja Knife | Doppler": 293.594035, "Navaja Knife | Tiger Tooth": 234.456145, "Navaja Knife | Marble Fade": 275.462015, "Navaja Knife | Ultraviolet": 130.58382, "Navaja Knife | Damascus Steel": 124.76567, "Navaja Knife | Rust Coat": 117.65772000000001, "Stiletto Knife | Doppler": 790.6543800000001, "Stiletto Knife | Marble Fade": 736.5198449999999, "Stiletto Knife | Tiger Tooth": 719.482925, "Stiletto Knife | Ultraviolet": 340.45763, "Stiletto Knife | Damascus Steel": 356.48976, "Stiletto Knife | Rust Coat": 271.87826000000007, "Talon Knife | Marble Fade": 1149.8428950000002, "Talon Knife | Doppler": 1428.4139349999998, "Talon Knife | Tiger Tooth": 1144.316725, "Talon Knife | Ultraviolet": 449.24179, "Talon Knife | Damascus Steel": 584.60312, "Talon Knife | Rust Coat": 498.19866000000013, "Ursus Knife | Marble Fade": 696.751225, "Ursus Knife | Doppler": 749.2318100000001, "Ursus Knife | Tiger Tooth": 563.43611, "Ursus Knife | Ultraviolet": 258.28488, "Ursus Knife | Damascus Steel": 240.91923000000003, "Ursus Knife | Rust Coat": 188.38542000000004}}, {"name": "Fracture Case", "cost": 0.64, "predict_cost": 1.572170027126555, "difference": 145.65156673852422, "total_return": 1.8392330609278158, "profitability_ratio": 58.761439646256086, "roi": -41.23856035374391, "average_prices": {"AK-47 | Legion of Anubis": 19.465010000000003, "Desert Eagle | Printstream": 71.05304000000001, "M4A4 | Tooth Fairy": 5.70871, "Glock-18 | Vogue": 5.9618899999999995, "XM1014 | Entombed": 5.48976, "Tec-9 | Brother": 0.7505600000000001, "MAG-7 | Monster Call": 0.73349, "MAC-10 | Allure": 0.7333200000000002, "Galil AR | Connexion": 0.7589100000000001, "MP5-SD | Kitbash": 0.74198, "SSG 08 | Mainframe 001": 0.14326999999999998, "P250 | Cassette": 0.12927000000000002, "P90 | Freight": 0.11679, "P2000 | Gnarled": 0.12083000000000002, "SG 553 | Ol' Rusty": 0.11613000000000001, "PP-Bizon | Runic": 0.11597000000000002, "Negev | Ultralight": 0.11552000000000001, "Nomad Knife | Fade": 1292.1841399999998, "Nomad Knife | Slaughter": 626.2354066666667, "Nomad Knife | Case Hardened": 356.64491000000004, "Nomad Knife | Crimson Web": 611.1303700000001, "Nomad Knife | Stained": 347.81132, "Nomad Knife | Blue Steel": 412.48017000000004, "Nomad Knife | Night Stripe": 242.87602, "Nomad Knife | Boreal Forest": 227.93209000000002, "Nomad Knife | Forest DDPAT": 207.30187, "Nomad Knife | Urban Masked": 227.98375000000001, "Nomad Knife | Scorched": 182.95007, "Nomad Knife | Safari Mesh": 195.95307000000003, "Paracord Knife | Fade": 944.1675150000001, "Paracord Knife | Night Stripe": 187.75449999999998, "Paracord Knife | Crimson Web": 403.79298, "Paracord Knife | Slaughter": 540.5253033333333, "Paracord Knife | Stained": 212.14702000000003, "Paracord Knife | Case Hardened": 346.70154, "Paracord Knife | Blue Steel": 245.97265000000002, "Paracord Knife | Safari Mesh": 151.03559, "Paracord Knife | Urban Masked": 156.59925, "Paracord Knife | Forest DDPAT": 152.56409, "Paracord Knife | Scorched": 155.37471, "Paracord Knife | Boreal Forest": 164.01174, "Skeleton Knife | Crimson Web": 1317.21347, "Skeleton Knife | Slaughter": 1252.4982033333333, "Skeleton Knife | Case Hardened": 878.5411800000003, "Skeleton Knife | Blue Steel": 650.05435, "Skeleton Knife | Urban Masked": 471.0427900000001, "Skeleton Knife | Night Stripe": 503.8573, "Skeleton Knife | Stained": 697.75141, "Skeleton Knife | Boreal Forest": 382.91046, "Skeleton Knife | Forest DDPAT": 407.95366, "Skeleton Knife | Scorched": 419.26128000000006, "Skeleton Knife | Safari Mesh": 388.00128, "Skeleton Knife | Fade": 1690.4928850000001, "Survival Knife | Fade": 721.846705, "Survival Knife | Slaughter": 493.61775666666665, "Survival Knife | Crimson Web": 479.94479, "Survival Knife | Case Hardened": 285.66591, "Survival Knife | Night Stripe": 199.48068, "Survival Knife | Blue Steel": 201.06502999999998, "Survival Knife | Stained": 200.84267000000003, "Survival Knife | Forest DDPAT": 154.11415, "Survival Knife | Boreal Forest": 153.9745, "Survival Knife | Scorched": 145.14912}}, {"name": "Operation Broken Fang Case", "cost": 4.2, "predict_cost": 4.722064325477819, "difference": 12.430102987567123, "total_return": 3.1149680447690002, "profitability_ratio": 46.56155522823617, "roi": -53.43844477176383, "average_prices": {"M4A1-S | Printstream": 234.57388000000006, "Glock-18 | Neo-Noir": 21.463440000000002, "M4A4 | Cyber Security": 20.083299999999998, "USP-S | Monster Mashup": 20.529120000000002, "Five-SeveN | Fairy Tale": 18.930799999999998, "AWP | Exoskeleton": 3.9928900000000005, "SSG 08 | Parallax": 2.5578500000000006, "UMP-45 | Gold Bismuth": 2.3613900000000005, "Nova | Clear Polymer": 2.24728, "Dual Berettas | Dezastre": 2.4425100000000004, "Galil AR | Vandal": 0.38198000000000004, "MP5-SD | Condition Zero": 0.40241, "P250 | Contaminant": 0.40882, "CZ75-Auto | Vendetta": 0.38826, "G3SG1 | Digital Mesh": 0.38548999999999994, "P90 | Cocoa Rampage": 0.38928, "M249 | Deep Relief": 0.37213, "Broken Fang Gloves | Jade": 258.8517, "Broken Fang Gloves | Yellow-banded": 151.60446000000002, "Broken Fang Gloves | Unhinged": 117.37584000000001, "Broken Fang Gloves | Needle Point": 101.25144, "Driver Gloves | Snow Leopard": 888.2064, "Driver Gloves | Black Tie": 372.15972, "Driver Gloves | Rezan the Red": 183.72618, "Driver Gloves | Queen Jaguar": 185.55498000000003, "Hand Wraps | CAUTION!": 329.04567, "Hand Wraps | Giraffe": 140.20398, "Hand Wraps | Constrictor": 97.01325, "Hand Wraps | Desert Shamagh": 103.82904, "Moto Gloves | Smoke Out": 322.76133, "Moto Gloves | Blood Pressure": 305.89704, "Moto Gloves | Finish Line": 285.04287, "Moto Gloves | 3rd Commando Company": 138.34682999999998, "Specialist Gloves | Field Agent": 502.41537, "Specialist Gloves | Tiger Strike": 787.5539099999999, "Specialist Gloves | Lt. Commander": 352.35522000000003, "Specialist Gloves | Marble Fade": 663.5868300000001, "Sport Gloves | Nocts": 490.95009000000005, "Sport Gloves | Slingshot": 941.6203200000001, "Sport Gloves | Big Game": 425.92131000000006, "Sport Gloves | Scarlet Shamagh": 446.42286}}, {"name": "Snakebite Case", "cost": 0.49, "predict_cost": 0.9656400183261122, "difference": 97.06939149512495, "total_return": 1.5935830556621666, "profitability_ratio": 53.47594146517337, "roi": -46.52405853482663, "average_prices": {"USP-S | The Traitor": 25.525650000000002, "M4A4 | In Living Color": 14.973139999999997, "MP9 | Food Chain": 3.4814300000000005, "Galil AR | Chromatic Aberration": 3.40182, "XM1014 | XOXO": 3.2136899999999993, "AK-47 | Slate": 5.675590000000001, "Desert Eagle | Trigger Discipline": 1.1019300000000003, "P250 | Cyber Shell": 0.5503199999999999, "Negev | dev_texture": 0.5326000000000001, "MAC-10 | Button Masher": 0.52684, "Glock-18 | Clear Polymer": 0.23045999999999997, "SG 553 | Heavy Metal": 0.20973000000000003, "R8 Revolver | Junk Yard": 0.21428, "CZ75-Auto | Circaetus": 0.21645, "Nova | Windblown": 0.23495, "UMP-45 | Oscillator": 0.20369000000000004, "M249 | O.S.I.P.R.": 0.20411, "Broken Fang Gloves | Jade": 258.8517, "Broken Fang Gloves | Yellow-banded": 151.60446000000002, "Broken Fang Gloves | Unhinged": 117.37584000000001, "Broken Fang Gloves | Needle Point": 101.25144, "Driver Gloves | Snow Leopard": 888.2064, "Driver Gloves | Black Tie": 372.15972, "Driver Gloves | Rezan the Red": 183.72618, "Driver Gloves | Queen Jaguar": 185.55498000000003, "Hand Wraps | CAUTION!": 329.04567, "Hand Wraps | Giraffe": 140.20398, "Hand Wraps | Constrictor": 97.01325, "Hand Wraps | Desert Shamagh": 103.82904, "Moto Gloves | Smoke Out": 322.76133, "Moto Gloves | Blood Pressure": 305.89704, "Moto Gloves | Finish Line": 285.04287, "Moto Gloves | 3rd Commando Company": 138.34682999999998, "Specialist Gloves | Field Agent": 502.41537, "Specialist Gloves | Tiger Strike": 787.5539099999999, "Specialist Gloves | Lt. Commander": 352.35522000000003, "Specialist Gloves | Marble Fade": 663.5868300000001, "Sport Gloves | Nocts": 490.95009000000005, "Sport Gloves | Slingshot": 941.6203200000001, "Sport Gloves | Big Game": 425.92131000000006, "Sport Gloves | Scarlet Shamagh": 446.42286}}, {"name": "Operation Riptide Case", "cost": 4.95, "predict_cost": 3.2842638412539404, "difference": -33.65123553022343, "total_return": 2.532646162263834, "profitability_ratio": 34.04094304118057, "roi": -65.95905695881945, "average_prices": {"Desert Eagle | Ocean Drive": 41.55577000000001, "AK-47 | Leet Museo": 36.760220000000004, "Glock-18 | Snack Attack": 6.745400000000001, "SSG 08 | Turbo Peek": 7.119360000000001, "MAC-10 | Toybox": 5.20898, "M4A4 | Spider Lily": 4.388419999999999, "FAMAS | ZX Spectron": 2.66922, "MP9 | Mount Fuji": 2.4418, "Five-SeveN | Boost Protocol": 1.9922, "MAG-7 | BI83 Spectrum": 1.3022700000000003, "USP-S | Black Lotus": 1.78102, "XM1014 | Watchdog": 0.47132999999999997, "AUG | Plague": 0.48895, "MP7 | Guerrilla": 0.3796800000000001, "PP-Bizon | Lumen": 0.42723000000000005, "Dual Berettas | Tread": 0.40548999999999996, "G3SG1 | Keeping Tabs": 0.40313000000000004, "Bowie Knife | Freehand": 220.28082, "Bowie Knife | Black Laminate": 225.5679, "Bowie Knife | Gamma Doppler": 632.676095, "Bowie Knife | Lore": 374.98493, "Bowie Knife | Autotronic": 283.90018, "Bowie Knife | Bright Water": 175.50885000000002, "Butterfly Knife | Autotronic": 1566.66813, "Butterfly Knife | Lore": 1252.51608, "Butterfly Knife | Black Laminate": 1183.7609800000002, "Butterfly Knife | Bright Water": 785.6391900000001, "Butterfly Knife | Freehand": 1084.9005000000002, "Butterfly Knife | Gamma Doppler": 943.479045, "Falchion Knife | Lore": 297.15773, "Falchion Knife | Autotronic": 277.62034000000006, "Falchion Knife | Gamma Doppler": 508.19081500000004, "Falchion Knife | Freehand": 209.15696, "Falchion Knife | Bright Water": 181.92321, "Falchion Knife | Black Laminate": 184.59156, "Huntsman Knife | Gamma Doppler": 699.3624100000001, "Huntsman Knife | Lore": 386.83651, "Huntsman Knife | Autotronic": 317.18854999999996, "Huntsman Knife | Black Laminate": 286.14032999999995, "Huntsman Knife | Freehand": 214.97923999999998, "Huntsman Knife | Bright Water": 196.48578, "Shadow Daggers | Lore": 256.16638, "Shadow Daggers | Gamma Doppler": 401.304385, "Shadow Daggers | Bright Water": 133.70808, "Shadow Daggers | Autotronic": 174.23627000000002, "Shadow Daggers | Black Laminate": 140.68784, "Shadow Daggers | Freehand": 158.72243000000003}}, {"name": "Dreams & Nightmares Case", "cost": 1.5, "predict_cost": 1.4118111974884586, "difference": -5.879253500769424, "total_return": 1.7742863200025003, "profitability_ratio": 44.4683288221178, "roi": -55.5316711778822, "average_prices": {"AK-47 | Nightwish": 46.825829999999996, "MP9 | Starlight Protector": 10.92048, "FAMAS | Rapid Eye Movement": 3.730410000000001, "Dual Berettas | Melondrama": 3.87628, "MP7 | Abyssal Apparition": 3.7633700000000005, "M4A1-S | Night Terror": 2.3526300000000004, "USP-S | Ticket to Hell": 1.45028, "PP-Bizon | Space Cat": 0.65519, "G3SG1 | Dream Glade": 0.5558099999999999, "XM1014 | Zombie Offensive": 0.55791, "MAC-10 | Ensnared": 0.16286, "Five-SeveN | Scrawl": 0.15738, "MP5-SD | Necro Jr.": 0.14690999999999999, "P2000 | Lifted Spirits": 0.14018999999999998, "SCAR-20 | Poultrygeist": 0.13924, "Sawed-Off | Spirit Board": 0.1405, "MAG-7 | Foresight": 0.14488, "Bowie Knife | Lore": 374.98493, "Bowie Knife | Gamma Doppler": 632.676095, "Bowie Knife | Autotronic": 283.90018, "Bowie Knife | Freehand": 220.28082, "Bowie Knife | Black Laminate": 225.5679, "Bowie Knife | Bright Water": 175.50885000000002, "Butterfly Knife | Gamma Doppler": 943.479045, "Butterfly Knife | Lore": 1252.51608, "Butterfly Knife | Autotronic": 1566.66813, "Butterfly Knife | Black Laminate": 1183.7609800000002, "Butterfly Knife | Bright Water": 785.6391900000001, "Butterfly Knife | Freehand": 1084.9005000000002, "Falchion Knife | Gamma Doppler": 508.19081500000004, "Falchion Knife | Lore": 297.15773, "Falchion Knife | Autotronic": 277.62034000000006, "Falchion Knife | Freehand": 209.15696, "Falchion Knife | Black Laminate": 184.59156, "Falchion Knife | Bright Water": 181.92321, "Huntsman Knife | Gamma Doppler": 699.3624100000001, "Huntsman Knife | Lore": 386.83651, "Huntsman Knife | Autotronic": 317.18854999999996, "Huntsman Knife | Black Laminate": 286.14032999999995, "Huntsman Knife | Freehand": 214.97923999999998, "Huntsman Knife | Bright Water": 196.48578, "Shadow Daggers | Lore": 256.16638, "Shadow Daggers | Gamma Doppler": 401.304385, "Shadow Daggers | Autotronic": 174.23627000000002, "Shadow Daggers | Black Laminate": 140.68784, "Shadow Daggers | Freehand": 158.72243000000003, "Shadow Daggers | Bright Water": 133.70808}}, {"name": "Recoil Case", "cost": 0.94, "predict_cost": 2.1785558086528107, "difference": 131.76125623966072, "total_return": 2.0848246528748335, "profitability_ratio": 60.78205985057823, "roi": -39.217940149421764, "average_prices": {"USP-S | Printstream": 95.93840000000002, "AWP | Chromatic Aberration": 30.107850000000003, "AK-47 | Ice Coaled": 20.925859999999997, "Sawed-Off | Kiss\u2665Love": 7.56865, "P250 | Visions": 7.71502, "Dual Berettas | Flora Carnivora": 1.4390700000000003, "R8 Revolver | Crazy 8": 1.44086, "SG 553 | Dragon Tech": 1.50309, "P90 | Vent Rush": 1.45444, "M249 | Downtown": 1.41733, "Glock-18 | Winterized": 0.2043, "M4A4 | Poly Mag": 0.23496000000000003, "FAMAS | Meow 36": 0.18504, "Galil AR | Destroyer": 0.18526, "Negev | Drop Me": 0.16520000000000004, "MAC-10 | Monkeyflage": 0.16439, "UMP-45 | Roadblock": 0.16159, "Broken Fang Gloves | Yellow-banded": 151.60446000000002, "Broken Fang Gloves | Jade": 258.8517, "Broken Fang Gloves | Needle Point": 101.25144, "Broken Fang Gloves | Unhinged": 117.37584000000001, "Driver Gloves | Snow Leopard": 888.2064, "Driver Gloves | Black Tie": 372.15972, "Driver Gloves | Rezan the Red": 183.72618, "Driver Gloves | Queen Jaguar": 185.55498000000003, "Hand Wraps | CAUTION!": 329.04567, "Hand Wraps | Desert Shamagh": 103.82904, "Hand Wraps | Giraffe": 140.20398, "Hand Wraps | Constrictor": 97.01325, "Moto Gloves | Smoke Out": 322.76133, "Moto Gloves | Finish Line": 285.04287, "Moto Gloves | Blood Pressure": 305.89704, "Moto Gloves | 3rd Commando Company": 138.34682999999998, "Specialist Gloves | Tiger Strike": 787.5539099999999, "Specialist Gloves | Marble Fade": 663.5868300000001, "Specialist Gloves | Field Agent": 502.41537, "Specialist Gloves | Lt. Commander": 352.35522000000003, "Sport Gloves | Slingshot": 941.6203200000001, "Sport Gloves | Nocts": 490.95009000000005, "Sport Gloves | Scarlet Shamagh": 446.42286, "Sport Gloves | Big Game": 425.92131000000006}}, {"name": "Revolution Case", "cost": 2.85, "predict_cost": 6.12759007662434, "difference": 115.00316058331018, "total_return": 3.6842183756025837, "profitability_ratio": 68.99285347570382, "roi": -31.007146524296186, "average_prices": {"M4A4 | Temukau": 143.83842, "AK-47 | Head Shot": 126.49249999999999, "AWP | Duality": 34.26484000000001, "UMP-45 | Wild Child": 19.31631, "P2000 | Wicked Sick": 19.09941, "M4A1-S | Emphorosaur-S": 5.0674800000000015, "Glock-18 | Umbral Rabbit": 3.10802, "R8 Revolver | Banana Cannon": 2.8769400000000007, "P90 | Neoqueen": 3.7446200000000003, "MAC-10 | Sakkaku": 4.8323800000000015, "SG 553 | Cyberforce": 0.46889, "MP5-SD | Liquidation": 0.49535, "MP9 | Featherweight": 0.47314, "MAG-7 | Insomnia": 0.46021, "P250 | Re.built": 0.45239, "Tec-9 | Rebel": 0.45084, "SCAR-20 | Fragments": 0.46149, "Driver Gloves | Imperial Plaid": 589.28418, "Driver Gloves | King Snake": 739.54728, "Driver Gloves | Overtake": 200.38464000000005, "Driver Gloves | Racing Green": 79.93070999999999, "Hand Wraps | Cobalt Skulls": 597.03696, "Hand Wraps | Overprint": 388.20896999999997, "Hand Wraps | Arboreal": 126.81009, "Hand Wraps | Duct Tape": 95.51357999999999, "Hydra Gloves | Case Hardened": 138.05667, "Hydra Gloves | Emerald": 101.71215000000001, "Hydra Gloves | Rattler": 86.70402, "Hydra Gloves | Mangrove": 80.06472, "Moto Gloves | POW!": 568.78596, "Moto Gloves | Polygon": 302.0976, "Moto Gloves | Turtle": 315.98055, "Moto Gloves | Transport": 146.78793000000002, "Specialist Gloves | Mogul": 356.04801000000003, "Specialist Gloves | Fade": 615.25386, "Specialist Gloves | Crimson Web": 462.65652, "Specialist Gloves | Buckshot": 115.02333000000002, "Sport Gloves | Omega": 876.5034300000002, "Sport Gloves | Vice": 1476.6886800000002, "Sport Gloves | Amphibious": 1063.4891400000001, "Sport Gloves | Bronze Morph": 288.11592}}]}